Workbook

Sheet Key Assumptions
A1: HUBSTOR → AWS S3 MIGRATION | KEY ASSUMPTIONS & CAVEATS
A2: These assumptions must be reviewed and validated before the migration programme is formally approved. Any change to these assumptions may materially affect costs, timelines, or feasibility.
A4: BUSINESS & SCOPE ASSUMPTIONS
A5: # | B5: Assumption | C5: Detail & Implication | D5: Status / Action Required
A6: A1 | B6: HubStor advanced features NOT included in new architecture | C6: We have NOT replicated HubStor-specific features such as content indexing, advanced discovery, legal hold workflow, or smart tiering intelligence. These are excluded because it is currently UNKNOWN whether these features are actively used by any CRL site or user. If any site relies on these features, additional tooling (e.g. AWS OpenSearch, Elasticsearch, or a third-party discovery layer) would need to be scoped and costed separately. | D6: ⚠ Validate with site leads before migration start
A7: A2 | B7: Discovery sites: potential divestitures not modelled | C7: Several Discovery sites (LEI, HER, GRO, KUO, SZG, FRE, LYO, EVR and others) may be subject to divestiture. This analysis is based on CURRENT usage and storage volumes across all sites. If sites are divested, storage volumes and costs will reduce — meaning our AWS cost will be LOWER than modelled, and savings will be HIGHER. No downside risk from divestitures. If divestitures happen mid-migration, adjust the relevant gateway and S3 bucket accordingly. | D7: ✅ Conservative (upside only if divestitures occur)
A8: A3 | B8: Contractual obligations & data retention policy not yet verified | C8: We have assumed a 6-month migration window (Jul–Dec 2026) and HubStor termination from Jan 2027. HOWEVER: HubStor's contract notice period, any early termination penalties, and site-specific data retention policies (e.g. regulatory holds, litigation hold) have NOT been formally reviewed. These may affect: (1) the earliest possible HubStor termination date, (2) which data can be deleted from Azure and when, and (3) minimum retention periods before data can be moved. Legal and compliance review MUST be completed before finalising the migration schedule. | D8: 🔴 CRITICAL — Legal/Compliance review required BEFORE approval
A9: A4 | B9: HubStor not used for regulated / validated GxP systems | C9: This analysis assumes HubStor does not hold data from GxP-regulated or computer-system-validated environments. If HubStor IS used as part of a validated system (e.g. LIMS, ELN, laboratory instrument data), then: (1) migration must follow a validated CSV/change control process, (2) IQ/OQ/PQ testing may be required, (3) migration timelines will extend significantly, and (4) QA/Regulatory sign-off is mandatory before cutover. Please confirm with QA, Regulatory, and IT Compliance that no validated systems write to HubStor. | D9: 🔴 CRITICAL — QA/Regulatory confirmation required
A10: A5 | B10: All migration work performed by CRL internal resources (no external vendor) | C10: The cost model includes ZERO external vendor or consultancy fees. All activities — AWS account setup, IAM configuration, Storage Gateway installation, DataSync migration jobs, connector testing, validation, and HubStor decommission — are assumed to be executed by CRL's internal Cloud/IT team. If external resource is required (e.g. AWS Professional Services, system integrator, or HubStor migration support), an additional cost of $50K–$150K should be budgeted. Internal resource time has not been separately costed (opportunity cost only). | D10: ⚠ Confirm internal resource availability before commitment
A11: A6 | B11: Azure Backup & DataBox: $3,000/mo additional charge included | C11: An additional $3,000/month Azure charge for Backup services and DataBox has been identified and IS included in this analysis as a separate line item in the current cost. This charge ceases when Azure is fully decommissioned (Dec 2026). It increases the true current Azure cost baseline and therefore increases the monthly saving. | D11: ✅ Included in cost model — verified $3,000/mo
A12: A7 | B12: AWS costs held flat for Year 1 (2027); 5% growth from Year 2 (2028) | C12: AWS storage and infrastructure pricing is assumed constant in 2027 (no growth). From 2028 onwards, data volume grows at 5% per year (conservative), increasing S3 storage costs. AWS list prices are not assumed to increase. Gateway appliance cost is amortised over 36 months. | D12: ✅ Conservative growth assumption
A13: A8 | B13: Storage Gateway: File Gateway VM on EC2 t3.xlarge (recurring $130/mo/site) | C13: AWS S3 File Gateway VM runs on EC2 t3.xlarge at each of the 5 sites ($130/mo/site = $650/mo total). This is a RECURRING monthly cost from the moment the Gateway goes live during migration. Gateway presents NFS/SMB file shares to applications, replacing HubStor connectors permanently. AWS Total post-migration = S3 $3,608 + Gateway EC2 $650 + ops $238 = $4,496/mo. | D13: ✅ EC2 Gateway $650/mo — recurring post-migration. AWS Total = $4,496/mo
A14: A9 | B14: HubStor costs based on Azure Blob Storage charges (from Master Report v5) | C14: The HubStor cost model uses actuals from HubStor Master Report v5. Monthly HubStor Azure Blob Storage charges = $26,455.17/mo across 5 regions. Azure Backup/DataBox = $3,000/mo. Total current baseline = $29,455.17/mo. | D14: ✅ Confirmed — actuals from HubStor Master Report v5
A15: MONEY STEP — WHAT WE ARE CHANGING AND HOW SAVINGS WILL BE MEASURED
A16: WHAT WE ARE SPECIFICALLY CHANGING: CRL currently pays $29,455/month ($353,462/year) for HubStor Azure Blob Storage ($26,455/mo) and Azure Backup/DataBox ($3,000/mo) to store 1,041.7 TiB of scientific and regulatory data across 5 Azure regions. This project migrates all data to AWS S3 using AWS S3 File Gateway (EC2 t3.xlarge at each site presenting NFS/SMB shares to applications), terminates the HubStor subscription, and decommissions all Azure Blob storage. The change replaces a recurring managed SaaS storage platform with directly-managed cloud object storage at $4,496/month — a saving of $24,959/month from January 2027.
A17: HOW SUCCESS WILL BE TRACKED AND MEASURED: (1) MONTHLY COST REDUCTION — AWS bill confirmed below $4,500/month (vs current $29,455/mo) from January 2027 onwards, verified through AWS Cost Explorer and monthly finance reporting. (2) HUBSTOR INVOICE TO $0 — HubStor subscription invoice confirmed as $0 from January 2027, evidenced by contract termination confirmation and final billing statement. (3) PAYBACK ACHIEVED — Net cumulative saving turns positive within ~5 months of migration completion, tracked in the Financial Model Net Cumulative Saving column. (4) DATA INTEGRITY VERIFIED — 100% object count match between HubStor export and S3 inventory confirmed before each site cutover, documented in the migration runbook sign-off. (5) 4-YEAR BENEFIT — Projected net saving of ~$1.08M over 4 years (Jan 2027–Dec 2030) against the one-time migration investment of ~$121,000, representing an 84.7% cost reduction.
A18: BENEFIT SUMMARY: Monthly saving = $24,959/mo (84.7% cost reduction) | Annual saving = $299,508/yr | One-time migration cost ≈ $121,000 | Payback ≈ 5 months from Jan 2027 | 4-Year net saving ≈ $1.08M
A20: This document is prepared for internal CRL review only. Costs are estimates based on published list pricing as of Q1 2026 and actual HubStor Master Report data. Final costs subject to AWS contract negotiations, Wasabi quote, and HubStor termination terms. Not for external distribution.

Sheet Assumptions
A1: CENTRAL ASSUMPTIONS — ALL INPUTS IN ONE PLACE
A2: Yellow = hardcoded inputs (change here) | All other sheets reference these cells | Black text = formula | Blue text = linked input
A4: STORAGE VOLUMES (from HubStor Master Report v5)
A5: Parameter | B5: Cell Ref | C5: Value | D5: Unit | E5: Source / Notes
A6: Standard tier GiB | B6: A6 | C6: 7775.51 | D6: GiB | E6: HubStor Master Report v5 actuals
A7: Hot tier GiB | B7: A7 | C7: 7401.73 | D7: GiB | E7: HubStor Master Report v5 actuals
A8: Cool tier GiB | B8: A8 | C8: 165555.92 | D8: GiB | E8: HubStor Master Report v5 actuals
A9: Cold tier GiB | B9: A9 | C9: 3195.69 | D9: GiB | E9: HubStor Master Report v5 actuals
A10: Archive tier GiB | B10: A10 | C10: 882775.79 | D10: GiB | E10: HubStor Master Report v5 actuals
A11: GiB → GB conversion factor | B11: A11 | C11: 1.074 | D11: × | E11: 1 GiB = 1.074 GB (decimal)
A12: GiB per TiB (divisor) | B12: A12 | C12: 1024 | D12: ÷ | E12: 1 TiB = 1024 GiB
A13: Total GiB (all tiers) | B13: A13 | C13: =C6+C7+C8+C9+C10 -> 1066704.6 | D13: GiB | E13: Sum of all five tiers
A14: Total TiB | B14: A14 | C14: =C13/C12 -> 1041.7038 | D14: TiB | E14: Total GiB ÷ 1,024
A15: Total GB (decimal) | B15: A15 | C15: =C13*C11 -> 1145640.8 | D15: GB | E15: Total GiB × 1.074 (for Azure/AWS pricing which uses decimal GB)
A16: US region GiB | B16: A16 | C16: =221472.95+72998.02 -> 294470.97 | D16: GiB | E16: EastUS2 + WestUS2 (from Master Report)
A17: EU region GiB | B17: A17 | C17: =374040.18+349749.29+48444.2 -> 772233.67 | D17: GiB | E17: UKSouth + WestEurope + GermanyWestCentral
A18: US region GB | B18: A18 | C18: =C16*C11 -> 316261.82 | D18: GB | E18: US GiB × 1.074
A19: EU region GB | B19: A19 | C19: =C17*C11 -> 829378.96 | D19: GB | E19: EU GiB × 1.074
A21: AZURE / HUBSTOR PRICING
A22: Parameter | B22: Cell Ref | C22: Value | D22: Unit | E22: Source / Notes
A23: Azure Standard/Hot $/GB/mo | B23: A23 | C23: 0.02 | D23: $/GB/mo | E23: Azure Blob Standard pricing (public)
A24: Azure Cool $/GB/mo | B24: A24 | C24: 0.015 | D24: $/GB/mo | E24: Azure Blob Cool tier
A25: Azure Cold $/GB/mo | B25: A25 | C25: 0.01 | D25: $/GB/mo | E25: Azure Blob Cold tier
A26: Azure Archive $/GB/mo | B26: A26 | C26: 0.002 | D26: $/GB/mo | E26: Azure Blob Archive tier
A27: Azure Cool retrieval $/GB | B27: A28 | C27: 0.01 | D27: $/GB | E27: Azure Blob Cool read charge
A28: Azure Cold retrieval $/GB | B28: A29 | C28: 0.03 | D28: $/GB | E28: Azure Blob Cold read charge
A29: Azure Archive rehydration $/GB | B29: A30 | C29: 0.022 | D29: $/GB | E29: Standard rehydration priority (~15hr wait)
A30: Azure egress tier1 $/GB | B30: A31 | C30: 0.087 | D30: $/GB | E30: 0–10 TB internet egress
A31: Azure egress tier2 $/GB | B31: A32 | C31: 0.083 | D31: $/GB | E31: 10–50 TB internet egress
A32: Azure egress tier3 $/GB | B32: A33 | C32: 0.07 | D32: $/GB | E32: 50–150 TB internet egress
A33: Azure egress tier4 $/GB | B33: A34 | C33: 0.05 | D33: $/GB | E33: >150 TB internet egress
A35: AWS PRICING
A36: Parameter | B36: Cell Ref | C36: Value | D36: Unit | E36: Source / Notes
A37: S3 Standard $/GB/mo (US) | B37: A38 | C37: 0.023 | D37: $/GB/mo | E37: AWS us-east-1 list price 2026
A38: S3 Standard $/GB/mo (EU) | B38: A39 | C38: 0.024 | D38: $/GB/mo | E38: AWS EU regions list price
A39: S3 Standard-IA $/GB/mo (US) | B39: A40 | C39: 0.0125 | D39: $/GB/mo | E39: AWS Standard-IA storage rate
A40: S3 Standard-IA $/GB/mo (EU) | B40: A41 | C40: 0.013 | D40: $/GB/mo | E40: AWS EU Standard-IA
A41: S3 Glacier IR $/GB/mo (US) | B41: A42 | C41: 0.004 | D41: $/GB/mo | E41: Glacier Instant Retrieval
A42: S3 Glacier IR $/GB/mo (EU) | B42: A43 | C42: 0.0045 | D42: $/GB/mo | E42: Glacier IR EU
A43: S3 Glacier Deep Archive $/GB/mo (US) | B43: A44 | C43: 0.00099 | D43: $/GB/mo | E43: Glacier Deep Archive (cheapest tier)
A44: S3 Glacier Deep Archive $/GB/mo (EU) | B44: A45 | C44: 0.001 | D44: $/GB/mo | E44: Glacier Deep Archive EU
A45: S3 Standard PUT $/1K requests | B45: A46 | C45: 0.005 | D45: $/1K | E45: PUT/COPY/POST/LIST Standard
A46: S3 Standard-IA PUT $/1K requests | B46: A47 | C46: 0.01 | D46: $/1K | E46: IA has higher PUT rate
A47: S3 Glacier Deep Archive PUT $/1K | B47: A48 | C47: 0.05 | D47: $/1K | E47: 10× Standard — file size matters
A48: S3 API operations overhead % | B48: A49 | C48: 0.02 | D48: % | E48: Estimated ongoing API/request costs as % of storage (conservative)
... A65: Azure Backup & DataBox monthly charge | B65: A66 | C65: 3000 | D65: $/mo | E65: Additional Azure charge for Backup services + DataBox. Ceases from Jan 2027 when Azure fully decommissioned.
A66: TOTAL current Azure + HubStor monthly (incl. Backup/DataBox) | B66: A67 | C66: =C64+C65 -> 29455.17 | D66: $/mo | E66: HubStor Azure Blob $26,455.17 + Azure Backup/DataBox $3,000 = $29,455.17/mo total

Sheet Revised Scope Estimate
A1: HUBSTOR → AWS S3 | REVISED SCOPE BUSINESS CASE | Discovery → Vendor | AWS Arivis Decommission
A2: Prepared for Internal Review | Revised Scope: Discovery sites + Arivis to vendor | Non-Discovery to AWS S3 | March 2026
A4: REVISED CURRENT TOTAL (HubStor + Backup + Arivis)
A5: =C53 -> 41455.17 | C5: =C99 -> 1625.84 | E5: =C53-C99 -> 39829.33 | G5: =D86 -> 121872.3
A6: ="$"&TEXT(C53*12,"#,##0")&"/yr | HubStor $26,455 + Backup $3,000 + Arivis $12,000" -> $497,462/yr | HubStor $26,455 + Backup $3,000 + Arivis $12,000 | C6: ="$"&TEXT(C99*12,"#,##0")&"/yr | S3 $998 + Gateway $390 + ops $238" -> $19,510/yr | S3 $998 + Gateway $390 + ops $238 | E6: =IFERROR(TEXT(C53-C99,"$#,##0")&"/mo | "&TEXT((C53-C99)/C53*100,"0.0")&"% cost reduction (AWS only)","see C53 minus C99") -> $39,829/mo | 96.1% cost reduction (AWS only) | G6: ="AWS ~$"&TEXT(D84,"#,##0")&" + Vendor ~$"&TEXT(D86-D84,"#,##0")&" (vendor fees TBD)" -> AWS ~$38,255 + Vendor ~$83,618 (vendor fees TBD)
A8: SCOPE SPLIT — What goes where
A9: DISCOVERY → NEW VENDOR PLATFORM 753.6 TiB | WestEurope + GermanyWC + UKSouth (Discovery) LEI, HER, GRO, KUO, SZG, FRE, LYO, EVR · FRI · CRP, HAR, PTH AWS Arivis ($12,000/mo) also transferred to vendor | E9: NON-DISCOVERY → AWS S3 (as originally planned) 288.1 TiB | EastUS2 + WestUS2 + UKSouth Safety Assessment MWN, WLM · RNO · EDI | 3 × File Gateway EC2 t3.xlarge AWS Total = $1,626/mo (S3 $998 + Gateway $390 + ops $238)
A11: ROI & 5-YEAR SAVINGS (AWS workstream — confirmed figures; vendor saving is additive)
A12: Confirmed AWS savings only shown below. Discovery/Arivis vendor savings will ADD to these figures once vendor is selected.
A13: Period | B13: Current Cost | C13: AWS Post-Mig Cost | D13: Gross AWS Saving | E13: One-Time Cost | F13: Net AWS Saving | G13: Cumulative Net | H13: Notes
A14: Monthly (Jan 2027+) | B14: =C53 -> 41455.17 | C14: =C99 -> 1625.84 | D14: =B14-C14 -> 39829.33 | E14: — | F14: =D14 -> 39829.33 | G14: — | H14: Monthly AWS saving. Vendor TBD (additive).
A15: Year 1 (2027) | B15: =C53*12 -> 497462.04 | C15: =C99*12 -> 19510.08 | D15: =B15-C15 -> 477951.96 | E15: =D84 -> 38254.7 | F15: =D15-E15 -> 439697.26 | G15: =F15 -> 439697.26 | H15: AWS one-time deducted in Year 1.
A16: Year 2 (2028) | B16: =C53*12 -> 497462.04 | C16: =C99*12*1.05 -> 20485.584 | D16: =B16-C16 -> 476976.46 | E16: 0 | F16: =D16 -> 476976.46 | G16: =G15+F16 -> 916673.72 | H16: AWS +5%/yr from Year 2.
A17: Year 3 (2029) | B17: =C53*12 -> 497462.04 | C17: =C99*12*1.05^2 -> 21509.863 | D17: =B17-C17 -> 475952.18 | E17: 0 | F17: =D17 -> 475952.18 | G17: =G16+F17 -> 1392625.9
A18: Year 4 (2030) | B18: =C53*12 -> 497462.04 | C18: =C99*12*1.05^3 -> 22585.356 | D18: =B18-C18 -> 474876.68 | E18: 0 | F18: =D18 -> 474876.68 | G18: =G17+F18 -> 1867502.6
A19: Year 5 (2031) | B19: =C53*12 -> 497462.04 | C19: =C99*12*1.05^4 -> 23714.624 | D19: =B19-C19 -> 473747.42 | E19: 0 | F19: =D19 -> 473747.42 | G19: =G18+F19 -> 2341250
A20: 5-YEAR TOTAL | B20: =C53*60 -> 2487310.2 | C20: =SUM(C15:C19) -> 107805.51 | D20: =B20-C20 -> 2379504.7 | E20: =D84 -> 38254.7 | F20: =D20-E20 -> 2341250 | G20: =G19 -> 2341250 | H20: 5-year net (AWS). Vendor saving additional.
A21: Payback — AWS workstream | C21: =IFERROR(D84/(C53-C99),0) -> 0.96046557 | E21: =IFERROR(TEXT(D84,"$#,##0")&" ÷ $"&TEXT(C53-C99,"#,##0")&"/mo = "&TEXT(D84/(C53-C99),"0.0")&" months from Jan 2027","Calculating...") -> $38,255 ÷ $39,829/mo = 1.0 months from Jan 2027
A23: VENDOR COST SENSITIVITY — Total saving at different vendor monthly costs (753 TiB Discovery + Arivis)
A24: Vendor monthly
A25: $4,000/mo | B25: $1,626/mo | C25: $5,626/mo | D25: $35,829/mo | E25: 86.4% | F25: ~3.2 mo | G25: Best case — aggressive discount
A26: $6,000/mo | B26: $1,626/mo | C26: $7,626/mo | D26: $33,829/mo | E26: 81.6% | F26: ~3.4 mo | G26: Optimistic — below HubStor EU rate
A27: $8,000/mo | B27: $1,626/mo | C27: $9,626/mo | D27: $31,829/mo | E27: 76.8% | F27: ~3.6 mo | G27: Base case — reasonable SaaS rate
A28: $10,000/mo | B28: $1,626/mo | C28: $11,626/mo | D28: $29,829/mo | E28: 72.0% | F28: ~3.9 mo | G28: Conservative — market rate
A29: $12,000/mo | B29: $1,626/mo | C29: $13,626/mo | D29: $27,829/mo | E29: 67.1% | F29: ~4.2 mo | G29: Break-even — matches Arivis cost alone
A30: $15,000/mo | B30: $1,626/mo | C30: $16,626/mo | D30: $24,829/mo | E30: 59.9% | F30: ~4.7 mo | G30: Downside — higher than expected
A33: ▼ DETAILED COST BREAKDOWN — Sections 1–6 below (scroll down for full itemised costs)
A45: REVISED SCOPE ESTIMATE — Discovery Sites to Vendor | Non-Discovery to AWS S3 | AWS Arivis Decommission
A46: SCOPE CHANGE: (1) All Discovery sites decommissioned from HubStor/Azure and transferred to new vendor platform. (2) Non-Discovery sites (US + UK Safety Assessment) migrate to AWS S3 as originally planned. (3) AWS Arivis ($12,000/mo) decommissioned and transferred to vendor platform. This estimate covers all three workstreams.
A48: SECTION 1 — CURRENT MONTHLY COSTS (Revised Baseline incl. AWS Arivis)
A49: # | B49: Cost Item | C49: Monthly ($) | D49: Annual ($) | E49: Notes
A50: 1 | B50: HubStor Azure Blob Storage (all sites, actuals from Master Report v5) | C50: 26455.17 | D50: =C50*12 -> 317462.04 | E50: Storage-only costs across 5 Azure regions. Includes Discovery + non-Discovery sites.
A51: 2 | B51: Azure Backup & DataBox | C51: 3000 | D51: =C51*12 -> 36000 | E51: Additional Azure charge for Backup services and DataBox. Ceases on decommission.
A52: 3 | B52: AWS Arivis (image analysis platform — to be decommissioned) | C52: 12000 | D52: =C52*12 -> 144000 | E52: NEW ITEM: AWS-hosted Arivis platform, $12,000/mo. To be transferred to vendor platform. Cost eliminates from AWS billing on transfer date.
A53: TOTAL CURRENT MONTHLY COST | C53: =SUM(C50:C52) -> 41455.17 | D53: =C53*12 -> 497462.04 | E53: HubStor $26,455 + Backup $3,000 + Arivis $12,000
A55: SECTION 2 — DATA SCOPE SPLIT (Discovery vs Non-Discovery)
A56: Discovery sites (LEI, HER, GRO, KUO, SZG, FRE, LYO, EVR, FRI, CRP, HAR, PTH) → vendor platform. Non-Discovery (MWN, WLM, RNO, EDI) → AWS S3 as originally planned.
B57: Scope | C57: Azure Region | D57: Sites | E57: Data Volume (GiB) | F57: Data Volume (TiB) | G57: Destination | H57: Notes
A58: V
A59: V | B59: DISCOVERY → VENDOR | C59: GermanyWestCentral (Frankfurt) | D59: FRI | E59: 48444.2 | F59: =E15/1024 -> 37.358105 | G59: Vendor platform | H59: Discovery DE. German data sovereignty must be maintained.
A60: V | B60: DISCOVERY → VENDOR | C60: UKSouth (London) — Discovery portion | D60: CRP, HAR, PTH | E60: 373502 | F60: =E16/1024 -> 0 | G60: Vendor platform | H60: Early Discovery UK (CRP 325 TiB + HAR 17 TiB) + Portishead Discovery (PTH 26 TiB).
A61: A | B61: NON-DISCOVERY → AWS S3 | C61: EastUS2 (Virginia) | D61: MWN, WLM | E61: 221472.95 | F61: =E17/1024 -> 0 | G61: AWS S3 | H61: Safety Assessment East, Microbial, RMS. As originally planned.
A62: A | B62: NON-DISCOVERY → AWS S3 | C62: WestUS2 (Washington) | D62: RNO | E62: 72998.02 | F62: =E18/1024 -> 0 | G62: AWS S3 | H62: Safety Assessment West. As originally planned.
A63: A | B63: NON-DISCOVERY → AWS S3 | C63: UKSouth — non-Discovery portion | D63: EDI | E63: 538 | F63: =E19/1024 -> 0 | G63: AWS S3 | H63: Safety Assessment UK only. Minimal volume (0.5 TiB).
B64: DISCOVERY TOTAL | E64: =SUM(D14:D16) -> 994757.75 | F64: =E20/1024 -> 37.358105 | G64: → VENDOR
B65: NON-DISCOVERY TOTAL (→ AWS S3) | E65: =SUM(D17:D19) -> 1424576.3 | F65: =E65/1024 -> 1391.1878 | G65: → AWS S3
A67: SECTION 3 — ONE-TIME MIGRATION / TRANSFER COSTS
A68: Two separate transfer workstreams: (A) AWS S3 migration for non-Discovery sites (same method as original plan, smaller volume). (B) Vendor platform transfer for Discovery sites + Arivis. Vendor ingestion costs are estimated — confirm with chosen vendor.
A69: # | B69: Cost Component | C69: Workstream | D69: Amount ($) | E69: Basis / Formula | F69: Notes
A70: A1 | B70: Azure retrieval fees (non-Discovery data only) | C70: AWS S3 migration | D70: 6293 | E70: =D70 -> 6293 | F70: Cool/Cold/Archive retrieval. Proportional to non-Discovery fraction (~27.7% of original $22,739).
A71: A2 | B71: Azure egress — non-Discovery to AWS S3 | C71: AWS S3 migration | D71: 17896 | E71: =D71 -> 17896 | F71: Internet egress Azure→S3 for 288 TiB. ~27.7% of original $64,645.
A72: A3 | B72: AWS DataSync fee (non-Discovery data) | C72: AWS S3 migration | D72: 3967 | E72: =D72 -> 3967 | F72: $0.0125/GB × 317,000 GB (288 TiB × 1.074).
A73: A4 | B73: S3 PUT requests (non-Discovery) | C73: AWS S3 migration | D73: 121 | E73: =D73 -> 121 | F73: Proportional to non-Discovery object count.
A74: A5 | B74: IAM, KMS, S3 bucket setup | C74: AWS S3 migration | D74: 1000 | E74: =D74 -> 1000 | F74: 3 S3 buckets (us-east-1, us-west-2, eu-west-2), IAM roles, KMS. Smaller scope.
A75: A6 | B75: File Gateway EC2 setup (3 sites: MWN, WLM/RNO, EDI) | C75: AWS S3 migration | D75: 1500 | E75: =D75 -> 1500 | F75: $500/site × 3 sites IT labour. Gateway for US + UK Safety Assessment only.
A76: A7 | B76: Testing, UAT & HubStor decommission | C76: AWS S3 migration | D76: 4000 | E76: =D76 -> 4000 | F76: UAT $2,500 + HubStor contract decommission $1,500.
A77: A8 | B77: Contingency 10% (AWS workstream) | C77: AWS S3 migration | D77: =SUM(D70:D76)*0.1 -> 3477.7 | E77: =D77 -> 3477.7 | F77: 10% of AWS migration subtotal.
A78: B1 | B78: Azure egress — Discovery data to vendor platform | C78: Vendor transfer | D78: 49728 | E78: =D78 -> 49728 | F78: 828,801 GB × $0.06/GB average egress. Largest single cost. Negotiate waiver with Azure.
A79: B2 | B79: Vendor platform ingestion fee (est.) | C79: Vendor transfer | D79: 8288 | E79: =D79 -> 8288 | F79: Estimated $0.01/GB × 828,801 GB. Confirm with chosen vendor — may vary significantly.
A80: B3 | B80: Vendor platform setup & configuration | C80: Vendor transfer | D80: 5000 | E80: =D80 -> 5000 | F80: Infrastructure setup, user access config, data validation. Internal IT labour estimate.
A81: B4 | B81: Arivis data transfer to vendor platform (est.) | C81: Vendor transfer | D81: 8000 | E81: =D81 -> 8000 | F81: Arivis image data export from AWS + ingestion to vendor. Estimated $8,000. Arivis vendor to confirm actual transfer scope and cost.
A82: B5 | B82: Testing, validation & Discovery site cutover | C82: Vendor transfer | D82: 5000 | E82: =D82 -> 5000 | F82: Data integrity checks, user acceptance testing across Discovery sites.
A83: B6 | B83: Contingency 10% (vendor workstream) | C83: Vendor transfer | D83: =SUM(D78:D82)*0.1 -> 7601.6 | E83: =D83 -> 7601.6 | F83: 10% of vendor transfer subtotal.
A84: SUBTOTAL — AWS S3 Migration (non-Discovery) | D84: =SUM(D70:D77) -> 38254.7
A85: SUBTOTAL — Vendor Transfer (Discovery + Arivis) | D85: =SUM(D78:D83) -> 83617.6
A86: GRAND TOTAL — ONE-TIME COSTS (BOTH WORKSTREAMS) | D86: =D84+D85 -> 121872.3 | E86: AWS migration + Vendor transfer. Subject to vendor quotation for ingestion fees.
A88: SECTION 4 — ONGOING MONTHLY COSTS (Post-Migration, from Jan 2027)
A89: Non-Discovery data on AWS S3 has known, modelled costs below. Discovery vendor platform and Arivis vendor costs are TBD — these must be obtained from the chosen vendor as part of the vendor selection process.
A90: # | B90: Resource | C90: Monthly ($) | D90: Annual ($) | E90: Status | F90: Notes
A91: C1 | B91: AWS S3 Storage — non-Discovery data only (288 TiB) | C91: 997.84 | D91: =C91*12 -> 11974.08 | E91: CONFIRMED | F91: S3 Standard/IA/Glacier IR/Deep Archive for 288 TiB. Grows 5%/yr from 2028.
A92: C2 | B92: File Gateway EC2 — 3 sites (MWN/WLM, RNO, EDI) × $130 | C92: 390 | D92: =C92*12 -> 4680 | E92: CONFIRMED | F92: 3 EC2 t3.xlarge for US + UK Safety Assessment sites only. Recurring monthly.
A93: C3 | B93: AWS ops (CloudWatch, KMS, SNS, Config, API, Glacier, egress) | C93: 238 | D93: =C93*12 -> 2856 | E93: CONFIRMED | F93: Fixed ops costs. Same as original model.
A94: D1 | B94: Discovery sites — vendor platform storage & access (753 TiB) | C94: TBD | D94: TBD | E94: ⚠ TBD — VENDOR QUOTE | F94: Must obtain from vendor. Depends on vendor pricing model. Budget estimate: $0.01–$0.05/GB/mo = $8,300–$41,500/mo. Wide range until vendor selected.
A95: D2 | B95: AWS Arivis — vendor platform equivalent | C95: TBD | D95: TBD | E95: ⚠ TBD — VENDOR QUOTE | F95: Arivis functionality at vendor. Could be included in D1 vendor contract or separate SaaS subscription. Current AWS cost = $12,000/mo — target to reduce.
A96: D3 | B96: Azure Blob Storage — ELIMINATED | C96: $0 | D96: $0 | E96: ✅ ELIMINATED | F96: All Azure Blob decommissioned. Zero ongoing Azure storage cost.
A97: D4 | B97: HubStor subscription — TERMINATED | C97: $0 | D97: $0 | E97: ✅ TERMINATED | F97: HubStor contract ended. $26,455/mo eliminated from Jan 2027.
A98: D5 | B98: AWS Arivis on AWS — DECOMMISSIONED | C98: $0 | D98: $0 | E98: ✅ DECOMMISSIONED | F98: $12,000/mo eliminated from AWS billing on vendor transfer date.
A99: AWS MONTHLY TOTAL (non-Discovery, confirmed) | C99: =SUM(C91:C93) -> 1625.84 | D99: =C99*12 -> 19510.08 | E99: S3 + Gateway EC2 + ops
A100: VENDOR MONTHLY COST: TBD — pending vendor selection and quotation. Target: total post-migration cost (AWS + vendor + Arivis equivalent) should be well below current $41,455/mo. Even at $8,000/mo vendor cost, total = $1,626 + $8,000 = $9,626/mo — a $31,829/mo saving (76.8% reduction).
A102: SECTION 5 — SAVING SUMMARY vs CURRENT BASELINE
A103: Metric | B103: Current | C103: Post-Migration (AWS) | D103: Post-Migration (Vendor TBD) | E103: Delta | F103: Notes
A104: HubStor storage cost | B104: =C9-C7-C8 -> 0 | C104: $0 | D104: $0 | E104: ELIMINATED | F104: Entire $26,455/mo removed
A105: Azure Backup/DataBox | B105: =C8 -> 0 | C105: $0 | D105: $0 | E105: ELIMINATED | F105: $3,000/mo removed
A106: AWS Arivis | B106: =C7+C8-C9+C9 -> 0 | C106: $0 | D106: TBD | E106: TRANSFERRED | F106: $12,000/mo from AWS → vendor (vendor cost TBD)
A107: AWS non-Discovery storage | B107: $0 | C107: =C55 -> 0 | D107: N/A | E107: NEW COST | F107: $1,626/mo AWS S3 + Gateway + ops
A108: Vendor (Discovery+Arivis) | B108: $0 | C108: N/A | D108: TBD | E108: TBD | F108: Vendor quote required
A109: TOTAL | B109: =C9 -> 0 | C109: =C55 -> 0 | D109: TBD | E109: TBD | F109: Confirmed AWS saving vs current total
A111: SECTION 6 — KEY ACTIONS & NEXT STEPS
A112: Priority | B112: Action | C112: Owner | D112: Timeline | E112: Impact if delayed | F112: Status
A113: 🔴 CRITICAL | B113: Select vendor platform for Discovery sites and Arivis | C113: Programme Director | D113: Week 1–2 | E113: Cannot plan vendor transfer costs or timeline without vendor selection | F113: Not started
A114: 🔴 CRITICAL | B114: Get vendor quote for Discovery data ingestion + ongoing storage | C114: Cloud Arch + Vendor | D114: Week 2–3 | E114: Section 4 vendor costs are unknown — financial case incomplete without this | F114: Not started
A115: 🔴 CRITICAL | B115: Obtain Arivis vendor transfer specification | C115: Arivis / App Team | D115: Week 1–2 | E115: Transfer cost and feasibility unknown. $12,000/mo saving depends on this | F115: Not started
A116: 🔴 HIGH | B116: Confirm HubStor contract notice period and termination date | C116: Legal | D116: Week 1 | E116: Contract lock-in could add up to $88,500 in overlap billing | F116: Not started
A117: ⚠ HIGH | B117: Scope Azure egress waiver request for vendor transfer (753 TiB) | C117: Cloud Arch | D117: Week 2 | E117: Azure egress to vendor estimated at $49,728 — waiver could save $30–50K | F117: Not started
A118: ⚠ HIGH | B118: Confirm which sites are Discovery vs non-Discovery with data owners | C118: Programme Mgr | D118: Week 1 | E118: Scope split assumptions (UK Discovery vs Safety Assessment) may need validation | F118: Not started
A119: ✅ PROCEED | B119: AWS S3 migration for non-Discovery sites — proceed as planned | C119: Cloud Arch | D119: Month 1–6 | E119: No change to original AWS migration plan. Smaller scope = lower cost/risk | F119: Ready to start

Sheet Executive Summary
A1: HUBSTOR → AWS S3 COMPLETE MIGRATION | BUSINESS CASE & COST ANALYSIS
A2: Prepared for Internal Review | Based on HubStor Master Report v5 | Costs as at March 2026
A4: CURRENT TOTAL MONTHLY COST (HubStor + Azure + Backup/DataBox) | D4: AWS TOTAL MONTHLY (S3 + Gateway appliance + infra) | G4: MONTHLY SAVING vs CURRENT COST (Total current − AWS) | J4: ONE-TIME MIGRATION COST
A5: =Assumptions!C66 -> 29455.17 | D5: ='Cost Comparison'!B39 -> 4496.0458 | G5: =Assumptions!C66-'Cost Comparison'!B39 -> 24959.124 | J5: ='Migration Plan & Costs'!C60 -> 121370.23
A6: ="$"&TEXT(Assumptions!C66*12,"#,##0")&"/yr | HubStor $26,455 storage + Backup $3,000 | 1,042 TiB | 5 regions" -> $353,462/yr | HubStor $26,455 storage + Backup $3,000 | 1,042 TiB | 5 regions | D6: ="$"&TEXT('Cost Comparison'!B39*12,"#,##0")&"/yr | S3 storage + Gateway appliance + all ops" -> $53,953/yr | S3 storage + Gateway appliance + all ops | G6: ="$"&TEXT((Assumptions!C66-'Cost Comparison'!B39)*12,"#,##0")&"/yr saved | 79.0% cost reduction" -> $299,509/yr saved | 79.0% cost reduction | J6: ="Payback: ~"&TEXT(('Migration Plan & Costs'!B60+'Financial Model (Jun26-Dec30)'!B11)/( Assumptions!C66-'Cost Comparison'!B39),"0.0")&" months from Jan 2027" -> Payback: ~5.7 months from Jan 2027
A8: CURRENT HUBSTOR COSTS BY AZURE REGION (Source: HubStor Master Report v5)
A9: Azure Region | B9: Azure Location | C9: Total Usage (GiB) | D9: Formula: GiB | E9: Storage Cost/mo ($) | F9: Total Cost/mo ($) | G9: Formula: Total
A10: EastUS2 | B10: Virginia, USA | C10: 221472.95 | D10: Hardcoded from Master Report | E10: 5798.59 | F10: =E10 -> 5798.59 | G10: =E10 -> 5798.59 | H10: HubStor Azure Blob Storage charge
A11: GermanyWestCentral | B11: Frankfurt, Germany | C11: 48444.2 | D11: Hardcoded from Master Report | E11: 1337.27 | F11: =E11 -> 1337.27 | G11: =E11 -> 1337.27 | H11: HubStor Azure Blob Storage charge
A12: UKSouth | B12: London, UK | C12: 374040.18 | D12: Hardcoded from Master Report | E12: 9432.17 | F12: =E12 -> 9432.17 | G12: =E12 -> 9432.17 | H12: HubStor Azure Blob Storage charge
A13: WestEurope | B13: Amsterdam, Netherlands | C13: 349749.29 | D13: Hardcoded from Master Report | E13: 8299.36 | F13: =E13 -> 8299.36 | G13: =E13 -> 8299.36 | H13: HubStor Azure Blob Storage charge
A14: WestUS2 | B14: Washington, USA | C14: 72998.02 | D14: Hardcoded from Master Report | E14: 1587.78 | F14: =E14 -> 1587.78 | G14: =E14 -> 1587.78 | H14: HubStor Azure Blob Storage charge
A15: GRAND TOTAL | B15: All 5 Azure Regions | C15: =SUM(C10:C14) -> 1066704.6 | D15: SUM(C10:C14) | E15: =SUM(E10:E14) -> 26455.17 | F15: =SUM(F10:F14) -> 26455.17 | G15: Storage Cost + Total (equal here — non-storage removed) | H15: HubStor Azure Blob Storage across all regions
A17: STORAGE BY AZURE TIER (all values from Assumptions sheet — change inputs there)
A18: Azure Tier | B18: Equiv. AWS Class | C18: Usage (GiB) | D18: Usage (TiB) | E18: % of Total
A19: Standard | B19: S3 Standard | C19: =Assumptions!C6 -> 7775.51 | D19: =C19/1024 -> 7.5932715 | E19: =C19/Assumptions!C13 -> 0.0072892811
A20: Hot | B20: S3 Standard | C20: =Assumptions!C7 -> 7401.73 | D20: =C20/1024 -> 7.228252 | E20: =C20/Assumptions!C13 -> 0.0069388749
A21: Cool | B21: S3 Standard-IA | C21: =Assumptions!C8 -> 165555.92 | D21: =C21/1024 -> 161.6757 | E21: =C21/Assumptions!C13 -> 0.15520315
A22: Cold | B22: S3 Glacier IR | C22: =Assumptions!C9 -> 3195.69 | D22: =C22/1024 -> 3.120791 | E22: =C22/Assumptions!C13 -> 0.0029958527
A23: Archive | B23: S3 Deep Archive | C23: =Assumptions!C10 -> 882775.79 | D23: =C23/1024 -> 862.08573 | E23: =C23/Assumptions!C13 -> 0.82757284
A24: TOTAL | C24: =Assumptions!C13 -> 1066704.6 | D24: =C24/1024 -> 1041.7038 | E24: =SUM(E19:E23) -> 1

Sheet Cost Comparison
A1: AZURE HUBSTOR vs AWS S3 — COMPLETE COST COMPARISON (Storage + All Infrastructure)
A2: Prepared for Internal Review | Based on HubStor Master Report v5 | Costs as at March 2026
A4: TIER PRICING ASSUMPTIONS (all rates from Assumptions sheet — edit there)
A5: Storage Tier | B5: Azure Tier | C5: Azure $/GB/mo | D5: Formula | E5: AWS Class | F5: AWS $/GB/mo (blended) | G5: Formula | H5: Min Duration | I5: Notes
A6: Standard/Hot | B6: Standard/Hot | C6: =Assumptions!C23 -> 0.02 | D6: =Assumptions!C22 -> Value | E6: S3 Standard | F6: =(Assumptions!C37+Assumptions!C38)/2 -> 0.0235 | G6: =Assumptions!C26 -> 0.002 | H6: None | I6: Active files; low % of total
A7: Cool | B7: Cool | C7: =Assumptions!C24 -> 0.015 | D7: =Assumptions!C23 -> 0.02 | E7: S3 Standard-IA | F7: =(Assumptions!C39+Assumptions!C40)/2 -> 0.01275 | G7: =Assumptions!C26 -> 0.002 | H7: 30 days | I7: Retrieval fee applies
A8: Cold | B8: Cold | C8: =Assumptions!C25 -> 0.01 | D8: =Assumptions!C24 -> 0.015 | E8: S3 Glacier IR | F8: =(Assumptions!C41+Assumptions!C42)/2 -> 0.00425 | G8: =Assumptions!C26 -> 0.002 | H8: 90 days | I8: Millisecond retrieval
A9: Archive | B9: Archive | C9: =Assumptions!C26 -> 0.002 | D9: =Assumptions!C25 -> 0.01 | E9: S3 Deep Archive | F9: =(Assumptions!C43+Assumptions!C44)/2 -> 0.000995 | G9: =Assumptions!C26 -> 0.002 | H9: 180 days | I9: Dominant tier — 83% of data
A11: MONTHLY COST COMPARISON BY STORAGE TIER
A12: Tier | B12: Usage (GiB) | C12: Usage (TiB) | D12: Formula: TiB | E12: Azure Storage $/mo | F12: Formula | G12: Azure Total $/mo | H12: Formula | I12: AWS Storage $/mo | J12: Formula | K12: Monthly Saving $ | L12: Formula
A13: Standard/Hot | B13: =Assumptions!C6+Assumptions!C7 -> 15177.24 | C13: =B13/1024 -> 14.821523 | D13: B13÷1024 | E13: =B13*Assumptions!C11*Assumptions!C23 -> 326.00712 | F13: B13×Assumptions CC23×1.074 (GiB→GB×$/GB) | G13: =E13 -> 326.00712 | H13: Azure storage × rate | I13: =B13*Assumptions!C11*(Assumptions!C37+Assumptions!C38)/2 -> 383.05836 | J13: B13×1.074×Blended Standard/Hot AWS price | K13: =G13-I13 -> -57.051245 | L13: Azure storage - AWS Storage = monthly saving per tier
A14: Cool | B14: =Assumptions!C8 -> 165555.92 | C14: =B14/1024 -> 161.6757 | D14: B14÷1024 | E14: =B14*Assumptions!C11*Assumptions!C24 -> 2667.1059 | F14: B14×Assumptions CC24×1.074 (GiB→GB×$/GB) | G14: =E14 -> 2667.1059 | H14: Azure storage × rate | I14: =B14*Assumptions!C11*(Assumptions!C39+Assumptions!C40)/2 -> 2267.04 | J14: B14×1.074×Standard-IA blended | K14: =G14-I14 -> 400.06588 | L14: Azure storage - AWS Storage = monthly saving per tier
A15: Cold | B15: =Assumptions!C9 -> 3195.69 | C15: =B15/1024 -> 3.120791 | D15: B15÷1024 | E15: =B15*Assumptions!C11*Assumptions!C25 -> 34.321711 | F15: B15×Assumptions CC25×1.074 (GiB→GB×$/GB) | G15: =E15 -> 34.321711 | H15: Azure storage × rate | I15: =B15*Assumptions!C11*(Assumptions!C41+Assumptions!C42)/2 -> 14.586727 | J15: B15×1.074×Glacier IR blended | K15: =G15-I15 -> 19.734984 | L15: Azure storage - AWS Storage = monthly saving per tier
A16: Archive | B16: =Assumptions!C10 -> 882775.79 | C16: =B16/1024 -> 862.08573 | D16: B16÷1024 | E16: =B16*Assumptions!C11*Assumptions!C26 -> 1896.2024 | F16: B16×Assumptions CC26×1.074 (GiB→GB×$/GB) | G16: =E16 -> 1896.2024 | H16: Azure storage × rate | I16: =B16*Assumptions!C11*(Assumptions!C43+Assumptions!C44)/2 -> 943.36069 | J16: B16×1.074×Glacier Deep Archive blended | K16: =G16-I16 -> 952.8417 | L16: Azure storage - AWS Storage = monthly saving per tier
A17: STORAGE SUBTOTAL | B17: =SUM(B13:B16) -> 1066704.6 | C17: =SUM(C13:C16) -> 1041.7038 | E17: =SUM(E13:E16) -> 4923.6371 | G17: =SUM(G13:G16) -> 4923.6371 | I17: =SUM(I13:I16) -> 3608.0458 | K17: =SUM(K13:K16) -> 1315.5913
A19: AWS INFRASTRUCTURE COSTS — S3 File Gateway VM (EC2 t3.xlarge per site → S3)
A20: Resource | B20: Qty | C20: Unit Cost /mo | D20: Monthly ($) | E20: Annual ($) | F20: Notes
A21: AWS S3 File Gateway VM — EC2 t3.xlarge (×5 sites, recurring monthly) | B21: =Assumptions!C53 -> 5 | C21: =Assumptions!C51 -> 130 | D21: =B21*C21 -> 650 | E21: =D21*12 -> 7800 | F21: EC2 t3.xlarge hosts File Gateway VM software at each site. $130/mo × 5 sites = $650/mo recurring. Gateway presents NFS/SMB shares to applications, caches data locally, syncs to S3. Replaces HubStor connector agents permanently.
A22: S3 Transfer Acceleration (optional — set $0 for archive) | B22: 1 | C22: =Assumptions!C52 -> 0 | D22: =B22*C22 -> 0 | E22: =D22*12 -> 0 | F22: Only needed if upload speed over long-distance WAN is critical. Archive workloads: $0.
A23: CloudWatch (monitoring, dashboards, alarms, logs) | B23: 1 | C23: =Assumptions!C54 -> 31 | D23: =B23*C23 -> 31 | E23: =D23*12 -> 372 | F23: Dashboards + custom metrics + CloudWatch alarms + log ingestion
A24: AWS KMS — Customer Managed Keys (1 per region × 5) | B24: =Assumptions!C56 -> 5 | C24: =Assumptions!C55 -> 1 | D24: =B24*C24 -> 5 | E24: =D24*12 -> 60 | F24: $1/key/mo × 5 regions = $5/mo. Encrypts S3 objects and Gateway cache.
A25: SNS — cost & health alert notifications | B25: 1 | C25: =Assumptions!C57 -> 2 | D25: =B25*C25 -> 2 | E25: =D25*12 -> 24 | F25: Alert topics for budget anomalies and Gateway connectivity issues
A26: AWS Config — compliance rule evaluation | B26: 1 | C26: =Assumptions!C58 -> 10 | D26: =B26*C26 -> 10 | E26: =D26*12 -> 120 | F26: GxP/regulatory config rules on S3 buckets. Object Lock compliance checks.
A27: S3 API Operations — ongoing PUTs/GETs (new archive writes) | B27: 1 | C27: =Assumptions!C59 -> 65 | D27: =B27*C27 -> 65 | E27: =D27*12 -> 780 | F27: Estimated monthly API cost for new data written from all 5 gateway sites
A28: Glacier Deep Archive retrieval fees (ongoing, est. 0.5%/mo) | B28: 1 | C28: =Assumptions!C60 -> 86 | D28: =B28*C28 -> 86 | E28: =D28*12 -> 1032 | F28: 0.5% of 862 TiB retrieved/mo × $0.02/GB restore fee
A29: S3 egress to internet (end-user retrieval, est.) | B29: 1 | C29: =Assumptions!C61 -> 39 | D29: =B29*C29 -> 39 | E29: =D29*12 -> 468 | F29: ~10% of retrieved data sent externally. Rest served within AWS/Gateway.
A30: INFRASTRUCTURE SUBTOTAL | D30: =SUM(D21:D29) -> 888 | E30: =SUM(E21:E29) -> 10656
A32: TOTAL COST SUMMARY — HUBSTOR (CURRENT) vs AWS S3 COMPLETE REPLACEMENT
A33: Line Item | B33: Monthly ($) | C33: Annual ($) | D33: Saving vs HubStor | E33: % Reduction | F33: Notes
A34: HubStor Azure Blob Storage (from Master Report v5) | B34: =Assumptions!C64 -> 26455.17 | C34: =Assumptions!C64*12 -> 317462.04 | D34: $0 | E34: — | F34: Actuals from HubStor Master Report v5 — Azure Blob Storage across 5 regions
A35: Azure Backup & DataBox (additional charge) | B35: =Assumptions!C65 -> 3000 | C35: =Assumptions!C65*12 -> 36000 | D35: $0 | E35: — | F35: Backup services + DataBox ($3,000/mo). Ceases Dec 2026 when Azure fully decommissioned.
A36: TOTAL CURRENT MONTHLY COST (ALL-IN) | B36: =B34+B35 -> 29455.17 | C36: =C34+C35 -> 353462.04 | D36: $0 | E36: Baseline for all saving calculations | F36: HubStor + Azure Blob + Backup/DataBox — this is what we actually pay today
A37: AWS S3 Storage Cost (all 5 tiers) | B37: =I17 -> 3608.0458 | C37: =I17*12 -> 43296.549 | D37: =B36-B37 -> 25847.124 | E37: =(B36-B37)/B36 -> 0.87750722 | F37: Pure S3 storage — Standard/IA/Glacier IR/Deep Archive
A38: AWS Infrastructure (File Gateway VM EC2 + ops) | B38: =D30 -> 888 | C38: =E30 -> 10656 | F38: File Gateway EC2 $650 + CloudWatch $31 + KMS $5 + SNS $2 + Config $10 + S3 API $65 + Glacier $86 + egress $39 = $888/mo
A39: AWS TOTAL (Storage + Infrastructure) | B39: =B37+B38 -> 4496.0458 | C39: =C37+C38 -> 53952.549 | D39: =B36-B39 -> 24959.124 | E39: =(B36-B39)/B36 -> 0.84735971 | F39: True monthly saving vs total current cost (incl. Backup/DataBox)

Sheet Migration Plan & Costs
A1: ONE-TIME MIGRATION COSTS — COMPLETE ITEMIZED BREAKDOWN (All formulas shown)
A2: All four cost components + AWS setup costs | Black = formula | Blue/Yellow = input | Route: Azure → Public internet → S3 (NOT via VPN)
A4: COMPONENT 1 — AZURE RETRIEVAL CHARGES (reading data out of Azure Blob before egress)
A5: ℹ Standard/Hot: no retrieval fee. Cool=$0.01/GB. Cold=$0.03/GB. Archive=$0.022/GB (Standard rehydration, ~15hr wait — factor into timeline)
A6: Azure Tier | B6: GiB (input) | C6: GB (decimal) | D6: Formula: GB | E6: Retrieval $/GB | F6: Formula | G6: Retrieval Cost ($) | H6: Formula | I6: Notes
A7: Standard | B7: =Assumptions!C6 -> 7775.51 | C7: =B7*Assumptions!C11 -> 8350.8977 | D7: B7×Assumptions!C11 (GiB→GB) | E7: 0 | F7: 0 | G7: 0 | H7: No charge — Standard tier: read freely at no cost | I7: No retrieval fee
A8: Hot | B8: =Assumptions!C7 -> 7401.73 | C8: =B8*Assumptions!C11 -> 7949.458 | D8: B8×Assumptions!C11 (GiB→GB) | E8: 0 | F8: 0 | G8: 0 | H8: No charge — Hot tier: read freely at no cost | I8: No retrieval fee
A9: Cool | B9: =Assumptions!C8 -> 165555.92 | C9: =B9*Assumptions!C11 -> 177807.06 | D9: B9×Assumptions!C11 (GiB→GB) | E9: =Assumptions!C27 -> 0.01 | F9: =Assumptions!C27 -> 0.01 | G9: =C9*E9 -> 1778.0706 | H9: C9×E9 (GB × retrieval rate) | I9: Per-GB read charge
A10: Cold | B10: =Assumptions!C9 -> 3195.69 | C10: =B10*Assumptions!C11 -> 3432.1711 | D10: B10×Assumptions!C11 (GiB→GB) | E10: =Assumptions!C28 -> 0.03 | F10: =Assumptions!C28 -> 0.03 | G10: =C10*E10 -> 102.96513 | H10: C10×E10 (GB × retrieval rate) | I10: Per-GB read charge
A11: Archive | B11: =Assumptions!C10 -> 882775.79 | C11: =B11*Assumptions!C11 -> 948101.2 | D11: B11×Assumptions!C11 (GiB→GB) | E11: =Assumptions!C29 -> 0.022 | F11: =Assumptions!C29 -> 0.022 | G11: =C11*E11 -> 20858.226 | H11: C11×E11 (GB × retrieval rate) | I11: Standard rehydration rate (15hr per batch)
A12: SUBTOTAL — AZURE RETRIEVAL | G12: =SUM(G7:G11) -> 22739.262 | H12: SUM(G7:G11) — sum all five tiers
A14: COMPONENT 2 — AZURE EGRESS CHARGES (direct to S3 public endpoint — NOT via VPN)
A15: ℹ VPN routing adds AWS transit/inspection costs. Use S3 public endpoints. Azure charges tiered egress: rates drop for higher volumes. First 100GB free.
A16: Region Group | B16: Volume (GB) | C16: Formula: Volume | D16: Tier1 $/GB ≤10TB | E16: Tier2 $/GB 10-50TB | F16: Tier3 $/GB 50-150TB | G16: Tier4 $/GB >150TB | H16: Egress Cost ($) | I16: Formula | J16: Notes
A17: US Regions (EastUS2 + WestUS2) | B17: =Assumptions!C18 -> 316261.82 | C17: Assumptions!C18 — US GiB × 1.074 | D17: =Assumptions!C30 -> 0.087 | E17: =Assumptions!C31 -> 0.083 | F17: =Assumptions!C32 -> 0.07 | G17: =Assumptions!C33 -> 0.05 | H17: 19494.4 | I17: eastus2+westus2 gib×1.074 then tiered: 100GB free + 9900GB×$0.087 + 40000GB×$0.083 + 100000GB×$0.070 + remainder×$0.050 | J17: Virginia→us-east-1, Washington→us-west-2
A18: EU Regions (UKSouth + WestEurope + GermanyWestCentral) | B18: =Assumptions!C19 -> 829378.96 | C18: Assumptions!C19 — EU GiB × 1.074 | D18: =Assumptions!C30 -> 0.087 | E18: =Assumptions!C31 -> 0.083 | F18: =Assumptions!C32 -> 0.07 | G18: =Assumptions!C33 -> 0.05 | H18: 45150.25 | I18: eu gib×1.074 tiered: 100GB free + 9900GB×$0.087 + 40000GB×$0.083 + 100000GB×$0.070 + remainder×$0.050 | J18: UK→eu-west-2, NL→eu-west-1, DE→eu-central-1
A19: SUBTOTAL — AZURE EGRESS | H19: =SUM(H17:H18) -> 64644.65 | I19: SUM(H17:H18) — sum US+EU egress
A21: COMPONENT 3 — AWS S3 PUT REQUEST CHARGES (ingress to AWS is free; API calls are not)
A22: ℹ PUT rate varies by storage class. Glacier Deep Archive = $0.05/1K (10× Standard). Average file size is critical — adjust yellow cells. Object count = GiB×1024÷avg_MB.
A23: Storage Class | B23: Volume (GiB) | C23: Avg File MB ← INPUT | D23: Object Count | E23: Formula: Object Count | F23: PUT Rate ($/1K) | G23: Formula | H23: PUT Cost ($) | I23: Formula | J23: Notes
A24: S3 Standard (Std+Hot) | B24: =Assumptions!C6+Assumptions!C7 -> 15177.24 | C24: 10 | D24: =(B24*1024)/C24 -> 1554149.4 | E24: (B24 gib × 1024 MB/GiB) ÷ C24 (avg MB per file)) | F24: =Assumptions!C45 -> 0.005 | G24: =Assumptions!C45 -> 0.005 | H24: =(D24/1000)*F24 -> 7.7707469 | I24: (object count ÷ 1000) × PUT rate) | J24: Low avg size — active files
A25: S3 Standard-IA (Cool) | B25: =Assumptions!C8 -> 165555.92 | C25: 50 | D25: =(B25*1024)/C25 -> 3390585.2 | E25: (B25 gib × 1024 MB/GiB) ÷ C25 (avg MB per file)) | F25: =Assumptions!C46 -> 0.01 | G25: =Assumptions!C46 -> 0.01 | H25: =(D25/1000)*F25 -> 33.905852 | I25: (object count ÷ 1000) × PUT rate) | J25: $0.01/1K — IA PUT rate higher
A26: S3 Glacier IR (Cold) | B26: =Assumptions!C9 -> 3195.69 | C26: 200 | D26: =(B26*1024)/C26 -> 16361.933 | E26: (B26 gib × 1024 MB/GiB) ÷ C26 (avg MB per file)) | F26: =Assumptions!C45 -> 0.005 | G26: =Assumptions!C45 -> 0.005 | H26: =(D26/1000)*F26 -> 0.081809664 | I26: (object count ÷ 1000) × PUT rate) | J26: Standard PUT rate
A27: S3 Glacier Deep Archive | B27: =Assumptions!C10 -> 882775.79 | C27: 500 | D27: =(B27*1024)/C27 -> 1807924.8 | E27: (B27 gib × 1024 MB/GiB) ÷ C27 (avg MB per file)) | F27: =Assumptions!C47 -> 0.05 | G27: =Assumptions!C47 -> 0.05 | H27: =(D27/1000)*F27 -> 90.396241 | I27: (object count ÷ 1000) × PUT rate) | J27: ⚠ $0.05/1K — 10× Standard; file size critical
A28: SUBTOTAL — S3 PUT REQUESTS | H28: =SUM(H24:H27) -> 132.15465 | I28: SUM(H24:H27) — sum all PUT tiers
A30: COMPONENT 4 — POST-INGESTION LIFECYCLE TRANSITION CHARGES
A31: ℹ BEST PRACTICE: PUT directly into target storage class using --storage-class flag in DataSync. This makes transition cost $0. Option B shown for reference only.
A32: Option | B32: Target Class | C32: Object Count | D32: Formula | E32: Transition $/1K | F32: Formula | G32: Transition Cost ($) | H32: Formula | I32: Recommendation
A33: OPTION A (recommended): PUT directly to target class | B33: All classes | C33: =D24+D25+D26+D27 -> 6769021.4 | D33: Sum of all object counts from PUT section | E33: 0 | F33: 0 | G33: 0 | H33: 0 — PUT directly into target class: no lifecycle transition | I33: ✅ Use --storage-class flag per DataSync task. Zero cost.
A34: OPTION B: Land in Standard, transition to Standard-IA | B34: Standard-IA | C34: =D25 -> 3390585.2 | D34: Cool object count from PUT section row D | E34: =Assumptions!C46 -> 0.01 | F34: =Assumptions!C46 -> 0.01 | G34: =(C34/1000)*E34 -> 33.905852 | H34: (object count ÷ 1000) × transition rate) | I34: Avoid — use Option A above
A35: OPTION B: Land in Standard, transition to Deep Archive | B35: Glacier Deep Archive | C35: =D27 -> 1807924.8 | D35: Archive object count from PUT section row D | E35: =Assumptions!C47 -> 0.05 | F35: =Assumptions!C47 -> 0.05 | G35: =(C35/1000)*E35 -> 90.396241 | H35: (object count ÷ 1000) × transition rate) | I35: ⚠ Most expensive — avoid for 882 TiB archive data
A38: COMPONENT 5 — AWS ONE-TIME SETUP & MIGRATION EXECUTION COSTS (complete HubStor replacement)
A39: Item | B39: Qty | C39: Formula: Qty | D39: Unit Cost ($) | E39: Formula | F39: Total Cost ($) | G39: Formula | H39: Notes
A40: AWS DataSync — data scanning/migration fee | B40: =Assumptions!C15 -> 1145640.8 | C40: Assumptions!C15 (total GB decimal) | D40: =Assumptions!C62 -> 0.0125 | E40: Assumptions!C63 ($0.0125/GB scanned) | F40: =B40*D40 -> 14320.51 | G40: qty × Unit cost | H40: One-time migration tool — $0.0125/GB for all data scanned
A41: File Gateway VM on EC2 t3.xlarge setup & config (5 sites) | B41: =Assumptions!C53 -> 5 | C41: Assumptions!C54 (number of sites) | D41: 500 | E41: Estimated IT labor per site (internal cost) | F41: =B41*D41 -> 2500 | G41: qty × Unit cost | H41: Launch EC2 t3.xlarge at each site, install File Gateway software, configure NFS/SMB shares, test connectivity to S3. $500/site IT config labour. EC2 recurring from launch: $130/mo/site.
A42: S3 bucket creation, lifecycle policies, tagging | B42: 1 | C42: Fixed | D42: 500 | E42: One-time AWS console/CLI setup | F42: =B42*D42 -> 500 | G42: qty × Unit cost | H42: 5 buckets × 5 regions, lifecycle rules, Object Lock config
A43: IAM roles, policies, KMS key setup | B43: 1 | C43: Fixed | D43: 500 | E43: One-time security config | F43: =B43*D43 -> 500 | G43: qty × Unit cost | H43: Gateway IAM role, DataSync role, bucket policies, KMS CMKs
A44: Testing, validation & UAT | B44: 1 | C44: Fixed | D44: 3000 | E44: Internal resource time estimate | F44: =B44*D44 -> 3000 | G44: qty × Unit cost | H44: Data integrity checks, retrieval tests, connector smoke tests
A45: HubStor subscription decommission & contract mgmt | B45: 1 | C45: Fixed | D45: 2000 | E45: Legal/admin for contract termination | F45: =B45*D45 -> 2000 | G45: qty × Unit cost | H45: Notice period management, final data verification, sign-off
A46: SUBTOTAL — AWS SETUP COSTS | F46: =SUM(F40:F45) -> 22820.51 | G46: SUM(F40:F45) — sum all setup costs
A48: TOTAL ONE-TIME MIGRATION COST — GRAND TOTAL SUMMARY
A49: Line Item | B49: Amount ($) | C49: Formula | D49: % of Total | E49: Formula | F49: Notes
A50: 1. Azure Retrieval Charges | B50: =G12 -> 22739.262 | C50: G12 (Component 1 subtotal) | D50: =B50/SUM(B50:B55) -> 0.18735452 | E50: B50÷Grand Total
A51: 2. Azure Egress Charges | B51: =H19 -> 64644.65 | C51: H19 (Component 2 subtotal) | D51: =B51/SUM(B50:B55) -> 0.53262359 | E51: B51÷Grand Total
A52: 3. AWS S3 PUT Requests | B52: =H28 -> 132.15465 | C52: H28 (Component 3 subtotal) | D52: =B52/SUM(B50:B55) -> 0.0010888555 | E52: B52÷Grand Total
A53: 4. Lifecycle Transitions | B53: =G33 -> 0 | C53: G33 — Component 4 Option A (=$0 if PUT directly) | D53: =B53/SUM(B50:B55) -> 0 | E53: B53÷Grand Total
A54: 5. AWS Setup & Execution Costs | B54: =F46 -> 22820.51 | C54: F46 — Component 5 subtotal | D54: =B54/SUM(B50:B55) -> 0.18802394 | E54: B54÷Grand Total
A55: Contingency (10%) | B55: =SUM(B50:B54)*0.1 -> 11033.658 | C55: SUM(B50:B54)×10% contingency buffer | D55: =B55/SUM(B50:B55) -> 0.090909091 | E55: B55÷Grand Total
A56: ★ GRAND TOTAL — ONE-TIME MIGRATION COST | C56: =SUM(B50:B55) -> 121370.23 | D56: SUM(B50:B55) — all five components + contingency
A58: ROI & PAYBACK ANALYSIS
A59: Metric | B59: Value | C59: Formula | D59: Notes
A60: Total One-Time Migration Cost | B60: =SUM(B50:B55) -> 121370.23 | C60: =SUM(B50:B55) -> 121370.23
A61: Monthly Saving (HubStor - AWS Total/mo) | B61: =Assumptions!C66-'Cost Comparison'!B39 -> 24959.124 | C61: Assumptions!C67 (HubStor $26,455 + Backup $3,000 = $29,455) minus Cost Comparison!B39 (AWS total)
A62: Payback Period (months) | B62: =(B60+'Financial Model (Jun26-Dec30)'!B11)/B61 -> 5.6864124 | C62: (Migration cost + AWS overlap in Phase 1) ÷ monthly saving = true payback from Jan 2027 | D62: Months from Jan 2027 until net cumulative saving turns positive. Matches Financial Model: H80 ÷ monthly saving = months to break-even.
A63: Year 1 Gross Saving (Jan–Dec 2027, 12 months × monthly saving) | B63: =B61*12 -> 299509.49 | C63: Monthly saving × 12 months. Migration cost is captured in Phase 1 (Jul–Dec 2026). | D63: Consistent with Financial Model Annual Summary Year 1 gross saving
A64: 4-Year Gross Saving (Jan 2027–Dec 2030, 48 months) | B64: =B61*48 -> 1198038 | C64: Monthly saving × 48 months (Years 1–4). Gross saving before migration investment.
A65: Net Cumulative Saving — end of Year 1 (Dec 2027) | B65: ='Financial Model (Jun26-Dec30)'!H81 -> 157581.61 | C65: From Financial Model cumulative net saving column — includes Phase 1 migration cost and AWS overlap. | D65: Consistent with Financial Model Annual Summary H81
A66: Net Cumulative Saving — end of Year 4 (Dec 2030) | B66: ='Financial Model (Jun26-Dec30)'!H84 -> 1039378 | C66: From Financial Model cumulative net saving — full 4-year net after all migration costs. | D66: Consistent with Financial Model Annual Summary H84

Sheet Risks & Assumptions
A1: RISKS & ASSUMPTIONS — COMPLETE HUBSTOR + AZURE BLOB REPLACEMENT WITH AWS S3
A2: Must be reviewed and signed off before project commencement | Owner = Cloud Architecture Team
A4: KEY ASSUMPTIONS
A5: # | B5: Category | C5: Assumption | D5: Basis / Source | E5: If Wrong — Impact | F5: Owner | G5: Status
A6: A1 | B6: Pricing | C6: AWS list pricing held flat for 3-year model | D6: AWS published list rates March 2026 | E6: Costs could rise — actual savings may be lower | F6: Cloud Arch | G6: Confirmed
A7: A2 | B7: Pricing | C7: HubStor storage costs = 100% of Azure Blob charges from Master Report v5 ($26,455.17/mo) | D7: HubStor Master Report v5 actuals | E7: Ratio may vary monthly — directionally correct | F7: Finance | G7: Confirmed
A8: A3 | B8: Pricing | C8: Azure egress billed at public internet rates (not VPN) | D8: Architecture decision — direct to S3 public endpoint | E8: VPN routing adds AWS transit cost ($0.02/GB) — adds ~$18K | F8: Cloud Arch | G8: Decision required
A9: A4 | B9: Data | C9: All 1,041.7 TiB migrated to AWS (no data deleted pre-migration) | D9: HubStor Master Report v5 — all stors migrated | E9: Smaller dataset = lower migration cost; larger = higher | F9: Programme Mgr | G9: TBC
A10: A5 | B10: Data | C10: Archive avg file size = 500MB (PUT cost sensitivity) | D10: Assumed; actual could range 1MB-2GB (see sensitivity table) | E10: At 1MB avg: PUT cost rises by $45K; at 100MB: negligible | F10: Data Team | G10: Verify before migration
A11: A6 | B11: Data | C11: 5% annual data growth rate | D11: Conservative industry estimate for scientific archives | E11: Higher growth = higher AWS costs but also higher HubStor costs | F11: Data Team | G11: TBC
A12: A7 | B12: Architecture | C12: 5 Storage Gateway VMs required (1 per major site) | D12: Site topology from Connector Details sheet — MWN, WLM, RNO, UK, EU | E12: More sites = higher EC2/EBS cost; fewer = simpler but single-site risk | F12: Cloud Arch | G12: Review with sites
A13: A8 | B13: Architecture | C13: File Gateway (NFS/SMB) replaces all HubStor connectors | D13: HubStor connector list has 17+ connectors — all routed via Gateway | E13: Connector incompatibility = custom integration effort | F13: App Teams | G13: Verify each connector
A14: A9 | B14: Architecture | C14: Direct Connect NOT required — public internet sufficient | D14: Gateway uses HTTPS/TLS; adequate for archive workloads | E14: Bandwidth constraint at peak rehydration may slow retrieval | F14: Network Team | G14: Monitor in pilot
A15: A10 | B15: Migration | C15: Archive rehydration takes 15hr per batch (Azure Standard priority) | D15: Azure documentation — Standard priority SLA | E15: Expedited priority ($0.03/GB extra) available if timeline too slow | F15: Cloud Arch | G15: Plan buffer weeks 3-4
A16: A11 | B16: Migration | C16: DataSync used for US data; Rclone for EU (avoids AWS-specific tooling) | D16: Best practice for cross-cloud migration | E16: Tool failure = manual fallback; add 2-week buffer | F16: Migration Team | G16: TBC
... A21: A16 | B21: Commercial | C21: Wasabi not selected — AWS chosen for S3 API compatibility and GxP compliance | D21: Technical decision | E21: Wasabi at $6.99/TB = slightly cheaper; recalculate if Wasabi selected | F21: Cloud Arch | G21: Decision confirmed
A22: TOP 5 KEY RISKS
A23: Ranked by Risk Score. These require immediate owner attention before migration programme approval.
A24: # | B24: Risk | C24: Likelihood | D24: Impact | E24: Risk Score | F24: Mitigation | G24: Residual | H24: Owner
A25: R1 | B25: HubStor contract lock-in Contract may require >30-day notice or early termination penalties. A 90-day notice period adds up to $88,500 in unexpected HubStor overlap billing. | C25: MEDIUM | D25: HIGH | E25: 🔴 HIGH | F25: Review HubStor contract IMMEDIATELY before programme approval. If notice >30 days, shift migration start date or budget overlap cost. | G25: MEDIUM | H25: Legal / Finance
A26: R2 | B26: Archive rehydration on critical path 882 TiB of Archive data requires 15hr/batch Azure rehydration. If not started in Month 1, it will single-handedly delay the Dec 2026 cutover by 4–8 weeks. | C26: HIGH | D26: HIGH | E26: 🔴 CRITICAL | F26: Start Archive rehydration Day 1 of migration. Run US and EU batches in parallel. Budget for Expedited rehydration ($0.03/GB) as fallback if timeline slips. | G26: MEDIUM | H26: Cloud Arch
A27: R3 | B27: HubStor connector incompatibility 17+ DPI, NAS and SAP connectors must route via File Gateway NFS/SMB. Any connector using proprietary HubStor APIs will fail silently after cutover. | C27: MEDIUM | D27: HIGH | E27: 🔴 HIGH | F27: Pilot all 17+ connector types in Month 2 (before full migration). Test each with 5 representative files. Engage HubStor for any proprietary connector docs. | G27: MEDIUM | H27: App Teams
A28: R4 | B28: GxP / regulated data in scope If HubStor stores GxP-regulated data, migration must follow 21 CFR Part 11 / EU Annex 11 change control. Failure triggers regulatory findings. | C28: LOW | D28: CRITICAL | E28: 🟡 MODERATE | F28: QA/Regulatory sign-off required BEFORE approval. If confirmed: validated migration partner, full change control, +8–12 weeks to schedule. | G28: LOW | H28: QA / Regulatory
A29: R5 | B29: Data sovereignty breach Misconfigured DataSync tasks could route EU/UK data through US AWS regions, violating GDPR and UK data protection requirements. | C29: LOW | D29: CRITICAL | E29: 🟡 MODERATE | F29: Enforce S3 bucket region with AWS SCP from Day 1. SCP blocks objects landing in wrong region regardless of DataSync config. | G29: LOW | H29: Cloud Arch / Legal
A31: KEY INTERDEPENDENCIES — 5 Critical Dependencies That Must Be Managed in Sequence
A32: A delay in any upstream item cascades to all downstream items. D1 and D2 are block-on items — migration cannot proceed without them.
A33: # | B33: Interdependency | C33: Upstream item (must happen first) | D33: Downstream impact | E33: If broken — consequence | F33: Owner | G33: When | H33: Action required
A34: D1 | B34: Contract review → migration start date | C34: Legal reviews HubStor notice period (links to R1) | D34: Migration calendar, Phase 1 budget, overlap cost calculation | E34: 90-day notice = migration must start April 2026 or $88,500 added in overlap billing. | F34: Legal | G34: NOW Month 0 | H34: Review HubStor contract BEFORE any spend approved.
A35: D2 | B35: GxP confirmation → migration methodology | C35: QA confirms whether GxP data is in HubStor (links to R4) | D35: Entire migration approach, tooling, timeline, and cost model | E35: GxP confirmed = change control required. +8–12 weeks. Cost model changes materially. | F35: QA / Regulatory | G35: NOW Month 0 | H35: Block-on item — cannot proceed without QA sign-off.
A36: D3 | B36: Archive rehydration → cutover dates | C36: Azure Archive rehydration starts Month 1, Week 1 (links to R2) | D36: US + EU cutover dates in Months 3–6, HubStor termination date | E36: 2-week delay = Dec 2026 cutover becomes Feb 2027. $58,910 extra HubStor billing. | F36: Cloud Arch | G36: Month 1 Week 1 | H36: Start Day 1 of migration — it is the critical path.
A37: D4 | B37: Connector validation → per-site go-live | C37: All 17+ connectors tested against Gateway NFS/SMB (links to R3) | D37: Per-site cutover gate — cannot cut over until all connectors pass UAT | E37: One failed connector at cutover = site stays on HubStor. Timeline slips. Cost continues. | F37: App Teams | G37: Month 2 Pilot | H37: Pilot all connector types Month 2. Fix before full rollout.
A38: D5 | B38: AWS setup → all migration activity | C38: AWS accounts, S3 buckets, IAM roles, KMS keys created | D38: DataSync tasks, Gateway launches, Object Lock, monitoring — all depend on this | E38: Misconfigured IAM = DataSync fails. Wrong bucket region = sovereignty breach. | F38: Cloud Arch | G38: Month 1 Week 1 | H38: Complete Week 1. Peer-review IAM before DataSync starts.

Sheet 6-Month Migration Plan
A1: 6-MONTH MIGRATION PLAN — COMPLETE HUBSTOR → AWS S3 REPLACEMENT
A2: Phased approach: Pilot → US Regions → EU Regions → Cutover | Data residency preserved throughout | HubStor runs in parallel until Month 6
A4: PHASE OVERVIEW — TIMELINE AT A GLANCE
A5: Phase | B5: Description | C5: Month 1 | D5: Month 2 | E5: Month 3 | F5: Month 4 | G5: Month 5 | H5: Month 6 | I5: Key Milestone | J5: Owner | K5: Budget Impact ($) | L5: Status
A6: Phase 0 | B6: Foundation & Procurement | C6: ██████ | I6: AWS accounts active, IAM ready, HubStor contract notice served | J6: Cloud Arch | K6: =SUM(F41:F43) -> 0 | L6: Not started
A7: Phase 1 | B7: Pilot Migration (RMS East US) | D7: ██████ | I7: RMS 914 GiB migrated; Gateway tested; data integrity verified | J7: Migration Team | K7: ~$500 AWS costs only | L7: Not started
A8: Phase 2 | B8: US Regions (EastUS2 + WestUS2) | E8: ██████ | I8: 294 TiB US data migrated; US sites cut over to S3 Gateway | J8: Migration Team | K8: =H17*0.27 -> 0 | L8: Not started
A9: Phase 3 | B9: EU UK Region (UKSouth) | F9: ██████ | I9: 374 TiB UK data migrated; UK sites cut over | J9: Migration Team | K9: =H17*0.35 -> 0 | L9: Not started
A10: Phase 4 | B10: EU Continent (WestEurope + Germany) | G10: ██████ | I10: 398 TiB EU/DE data migrated; all EU sites cut over | J10: Migration Team | K10: =H17*0.38 -> 0 | L10: Not started
A11: Phase 5 | B11: Cutover, Decommission & Optimisation | H11: ██████ | I11: HubStor subscription cancelled; zero Azure Blob spend | J11: Cloud Arch / Finance | K11: First full month saving realised | L11: Not started
A13: PHASE 0 — FOUNDATION & PROCUREMENT (Month 1: Weeks 1-4)
A14: Week | B14: Category | C14: Task | D14: Owner | E14: Detail / Notes | F14: Success Criteria
A15: Week 1 | B15: Commercial | C15: Review and serve HubStor contract termination notice (verify notice period) | D15: Legal / Finance | E15: Notice period clock starts. If >30 days, adjust plan. | F15: CONTRACT NOTICE SERVED
A16: Week 1 | B16: AWS Setup | C16: Create AWS accounts per region (us-east-1, us-west-2, eu-west-2, eu-west-1, eu-central-1) | D16: Cloud Arch | E16: 5 AWS accounts or 1 org with SCPs per region | F16: Accounts active
A17: Week 1 | B17: AWS Setup | C17: Configure IAM: DataSync role, Gateway role, S3 bucket policies, KMS CMKs (1 per region) | D17: Cloud Arch | E17: All permissions least-privilege; tested with CLI | F17: IAM complete
A18: Week 2 | B18: AWS Setup | C18: Create S3 buckets with naming convention, Object Lock (Compliance mode), versioning policy | D18: Cloud Arch | E18: Bucket policy blocks public access; Object Lock enabled on GxP buckets | F18: Buckets created
A19: Week 2 | B19: AWS Setup | C19: Configure S3 lifecycle rules: Archive→Glacier Deep Archive on upload; Cool→Standard-IA | D19: Cloud Arch | E19: Lifecycle rules prevent objects landing in wrong tier | F19: Rules active
A20: Week 2 | B20: Monitoring | C20: Deploy CloudWatch dashboards: cost, storage usage, Gateway health, DataSync job status | D20: Cloud Arch | E20: Alerts configured for 120% budget threshold | F20: Dashboards live
A21: Week 3 | B21: Network | C21: Gateway VM deployment — install on-prem at WLM (pilot site). Configure NFS/SMB share | D21: Network + Cloud | E21: VM: m5.xlarge compatible VM on-prem. Attach 1TB EBS cache. Test HTTPS to S3. | F21: WLM Gateway online
A22: Week 3 | B22: Network | C22: Configure AWS VPC Gateway Endpoint for S3 (free — eliminates NAT Gateway fees if EC2 used) | D22: Cloud Arch | E22: Endpoint policy restricts access to specific buckets | F22: VPC endpoint active
A23: Week 4 | B23: Testing | C23: End-to-end connectivity test: write test file via Gateway → verify in S3 bucket → retrieve | D23: Migration Team | E23: Checksum match confirms data integrity path | F23: E2E test PASSED
A24: Week 4 | B24: Documentation | C24: Finalise migration runbook per site. DataSync job scripts prepared. Rollback plan documented | D24: Migration Team | E24: Runbook peer-reviewed | F24: Runbook signed off
A27: PHASE 1 — PILOT MIGRATION: RMS EAST US FILES (Month 2: ~914 GiB)
A28: Week | B28: Category | C28: Task | D28: Owner | E28: Detail / Notes | F28: Success Criteria
A29: Week 5 | B29: Migration | C29: Configure AWS DataSync: source=WLM-PR-FIL-05 Azure Blob, dest=S3 us-east-1 bucket | D29: Migration Team | E29: 3 DataSync tasks (3 connectors); --storage-class=STANDARD_IA for RMS data | F29: DataSync jobs configured
A30: Week 5 | B30: Migration | C30: Start DataSync transfer. Monitor CloudWatch for transfer rate, errors, throughput | D30: Migration Team | E30: Expected: ~200GB/hr → 914 GiB ≈ 5 hours. Run overnight. | F30: Transfer started
A31: Week 6 | B31: Validation | C31: Post-transfer: S3 Inventory report vs HubStor export — compare object counts and sizes | D31: Migration Team | E31: 100% object count match required before proceeding | F31: Integrity VERIFIED
A32: Week 6 | B32: Validation | C32: Retrieval test: retrieve 5 random files via S3 Gateway share. Verify content matches | D32: App Teams | E32: All 5 files open correctly; no corruption | F32: Retrieval PASSED
A33: Week 6 | B33: Cutover | C33: Update WLM-RMS connector to point to S3 File Gateway NFS share (change target path only) | D33: App Teams / Network | E33: Connector writes to S3 from this point; reads via Gateway cache | F33: Connector switched
A34: Week 7 | B34: Monitoring | C34: Monitor RMS connector for 1 week: write speed, retrieval latency, error rate | D34: Cloud Arch | E34: Target: <5s for cached reads; <30min for uncached archive fetch | F34: 1-week soak PASS
A35: Week 8 | B35: Review | C35: Pilot retrospective: document lessons, adjust runbook, confirm Phase 2 go/no-go | D35: Programme Mgr | E35: Signed go/no-go decision gate | F35: GO/NO-GO DECISION
A38: PHASE 2 — US REGIONS: EastUS2 + WestUS2 (Month 3: ~294 TiB)
A39: Week | B39: Category | C39: Task | D39: Owner | E39: Detail / Notes | F39: Success Criteria
A40: Week 9 | B40: Migration | C40: Begin archive rehydration for Safety Assessment East US (119 TiB archive). Submit rehydration job. | D40: Migration Team | E40: Azure Standard rehydration = up to 15hr. Batch by stor group. | F40: Rehydration started
A41: Week 9 | B41: Migration | C41: Deploy Gateway VM at MWN site (Safety Assessment). Configure connectors. | D41: Cloud Arch | E41: Mirror WLM setup. Same EBS cache size. Test connectivity. | F41: MWN Gateway ready
A42: Week 9 | B42: Migration | C42: Deploy Gateway VM at RNO site (Safety Assessment West). Configure connectors. | D42: Cloud Arch | E42: RNO covers WestUS2 data. | F42: RNO Gateway ready
A43: Week 10 | B43: Migration | C43: Start DataSync jobs: Microbial East US (25 TiB), RMS sub-stores remaining | D43: Migration Team | E43: Run overnight. Monitor DataSync CloudWatch dashboard. | F43: Microbial migrated
A44: Week 10 | B44: Migration | C44: Start DataSync jobs: Safety Assessment East US (after rehydration completes) | D44: Migration Team | E44: 122 TiB total. Largest US store. May take 2-3 nights. | F44: SA East migrated
A45: Week 11 | B45: Migration | C45: Start DataSync jobs: Safety Assessment West US (72 TiB WestUS2 data) | D45: Migration Team | E45: RNO connector data. Run over 2 nights. | F45: SA West migrated
A46: Week 11 | B46: Validation | C46: S3 Inventory cross-check for all US stores. Fix any gaps. | D46: Migration Team | E46: Zero discrepancy required | F46: US inventory matched
A47: Week 12 | B47: Cutover | C47: Switch all US site connectors to S3 Gateway. Disable Azure write access to US Blob containers. | D47: App Teams | E47: Connectors: APO-PR-APP-02 to 09, MWN-PR-FIL-01, WLM-PR-FIL-05 | F47: US sites LIVE on S3
A50: PHASE 3 — EU UK: UKSouth (Month 4: ~374 TiB)
A51: Week | B51: Category | C51: Task | D51: Owner | E51: Detail / Notes | F51: Success Criteria
A52: Week 13 | B52: Migration | C52: Deploy Gateway VM in UK DC (PTH/Portishead or EDI/Edinburgh). Configure eu-west-2 bucket. | D52: Cloud Arch | E52: UK data must stay in eu-west-2 (London). Enforce with SCP. | F52: UK Gateway ready
A53: Week 13 | B53: Migration | C53: Begin Early Discovery UK rehydration (242 TiB archive in UKSouth — largest single store) | D53: Migration Team | E53: Submit Azure rehydration. Expect 15-20 hours. Plan 2-3 day window. | F53: Rehydration queued
A54: Week 14 | B54: Migration | C54: Start DataSync: Portishead Discovery (26 TiB). Run overnight. | D54: Migration Team | E54: PTH-Discovery connector data. | F54: PTH migrated
A55: Week 14 | B55: Migration | C55: Start DataSync: Safety Assessment UK (525 GiB). Quick transfer. | D55: Migration Team | E55: EDI-SafetyAssessment — small store. | F55: EDI migrated
A56: Week 15 | B56: Migration | C56: Start DataSync: Early Discovery UK (325 TiB total after rehydration) | D56: Migration Team | E56: Largest EU store. Will take 3-4 nights. CRP (325 TiB) + HAR (17 TiB). | F56: UK Early Discovery migrated
A57: Week 16 | B57: Validation | C57: UK S3 Inventory cross-check. Validate Object Lock applied to regulated data. | D57: Migration + QA | E57: QA sign-off required for GxP stores | F57: UK inventory + GxP PASS
A58: Week 16 | B58: Cutover | C58: Switch UK connectors to S3 Gateway. Verify GDPR data residency in eu-west-2. | D58: App Teams / Legal | E58: Connectors: APO-PR-APP-03,04,11,12,14; MWN-PR-FIL-01 | F58: UK LIVE on S3
A61: PHASE 4 — EU CONTINENT: WestEurope + GermanyWestCentral (Month 5: ~398 TiB)
A62: Week | B62: Category | C62: Task | D62: Owner | E62: Detail / Notes | F62: Success Criteria
A63: Week 17 | B63: Migration | C63: Deploy Gateway VMs: Leiden NL (LEI) → eu-west-1 bucket; Freiburg DE (FRI) → eu-central-1 | D63: Cloud Arch | E63: German data MUST use eu-central-1 (Frankfurt). SCP enforced. | F63: EU/DE Gateways ready
A64: Week 17 | B64: Migration | C64: Begin Early Discovery NL rehydration (258 TiB archive). Submit to Azure. | D64: Migration Team | E64: WestEurope LEI-EarlyDiscovery. Largest EU store. | F64: NL rehydration queued
A65: Week 18 | B65: Migration | C65: Start DataSync: Discovery NL (3.9 TiB), Safety Assessment NL (18 TiB), Discovery HU (35 GiB) | D65: Migration Team | E65: Smaller stores first. Validate before tackling large NL store. | F65: Small EU stores migrated
A66: Week 18 | B66: Migration | C66: Start DataSync: Discovery DE (49 TiB into eu-central-1/Frankfurt) | D66: Migration Team | E66: FRI-Discovery. German data stays in DE. Validate region after. | F66: DE migrated
A67: Week 19 | B67: Migration | C67: Start DataSync: Discovery FI (38 TiB into eu-west-1) | D67: Migration Team | E67: KUO-Discovery. Finnish data via Amsterdam region. | F67: FI migrated
A68: Week 19 | B68: Migration | C68: Start DataSync: Early Discovery NL (286 TiB after rehydration) | D68: Migration Team | E68: Biggest EU migration. Run over 4-5 nights. | F68: NL Early Discovery migrated
A69: Week 20 | B69: Validation | C69: Full EU inventory cross-check. German data residency confirmed. FR/NL/FI/HU data in eu-west-1. | D69: Migration + Legal | E69: Data residency audit report produced | F69: EU inventory + residency PASS
A70: Week 20 | B70: Cutover | C70: Switch all EU connectors to S3 Gateway. Disable Azure EU Blob write access. | D70: App Teams | E70: All APO and FIL connectors for EU sites | F70: ALL EU LIVE on S3
A73: PHASE 5 — CUTOVER, DECOMMISSION & OPTIMISATION (Month 6)
A74: Week | B74: Category | C74: Task | D74: Owner | E74: Detail / Notes | F74: Success Criteria
A75: Week 21 | B75: Cutover | C75: Final validation: all sites reading/writing from S3 for 2 weeks. Zero Azure Blob writes. | D75: Cloud Arch | E75: CloudWatch confirms 0 bytes written to Azure | F75: Zero-Azure confirmed
A76: Week 21 | B76: Cutover | C76: Run full S3 Inventory vs original HubStor Master Report — final count match | D76: Migration Team | E76: 100% object count and size match required | F76: FINAL INTEGRITY PASS
A77: Week 21 | B77: Commercial | C77: Submit HubStor subscription cancellation. Provide data deletion confirmation if required. | D77: Finance / Legal | E77: Contract termination executed. Confirm no auto-renewal. | F77: HubStor CANCELLED
A78: Week 22 | B78: Commercial | C78: Terminate Azure Blob Storage accounts (all 5 regions). Download final invoices. | D78: Finance / Cloud Arch | E78: Azure cost stops. Final invoice received. | F78: Azure Blob TERMINATED
A79: Week 22 | B79: Optimisation | C79: Enable S3 Storage Lens — review storage efficiency, lifecycle policy effectiveness | D79: Cloud Arch | E79: Identify any objects in wrong tier; fix lifecycle rules | F79: Storage Lens active
A80: Week 22 | B80: Optimisation | C80: Enable Cost Anomaly Detection — alert if AWS bill exceeds $X,000 | D80: Finance | E80: Anomaly detector configured; tested with manual trigger | F80: Cost alerts live
A81: Week 23 | B81: Monitoring | C81: First clean month: AWS-only bill. Reconcile vs cost model. Report actual vs projected saving. | D81: Finance | E81: Report to stakeholders: actual vs $30,961 monthly saving target | F81: Month 1 saving report
A82: Week 24 | B82: Closeout | C82: Migration project retrospective. Update runbooks. Archive project docs. Celebrate! 🎉 | D82: Programme Mgr | E82: Lessons learned documented; team recognised | F82: PROJECT CLOSED

Sheet Financial Model (Jun26-Dec30)
A1: FINANCIAL MODEL — Jun 2026 to Dec 2030 | Migration Period + 4-Year AWS TCO
A2: Jul 1 – Dec 31 2026: RAMPED migration — AWS grows as data moves. Jan 2027: full AWS saving realised.
A4: MODEL INPUTS — all linked to Assumptions & Cost Comparison (change values there)
A5: HubStor + Azure monthly cost (incl. Backup/DataBox $3,000/mo) | B5: =Assumptions!C66 -> 29455.17
A6: AWS Total monthly — storage + Gateway appliance + all infra | B6: ='Cost Comparison'!B39 -> 4496.0458
A7: One-time migration cost (total) | B7: ='Migration Plan & Costs'!C60 -> 121370.23
A8: Annual data growth rate (applied from 2028 onwards) | B8: =Assumptions!C63 -> 0.05
A9: Monthly saving once fully on AWS (B5 − B6) | B9: =B5-B6 -> 24959.124
A10: Migration period (months: Jun–Dec 2026) | B10: 6
A11: AWS costs already paid during migration overlap (Jul–Dec 2026) | B11: =SUM(D17:D22) -> 20557.64 | C11: Sum of AWS ramp-up costs during migration (Jul–Dec). These must also be recovered from savings.
A12: Payback — months from Jan 2027 (migration cost + AWS overlap ÷ monthly saving) | B12: =(B7+B11)/B9 -> 5.6864124 | C12: =TEXT((B7+B11)/B9,"0.0")&" months from Jan 2027 ≈ May 2027 | (migration $121,370 + AWS overlap $24,791) ÷ monthly saving" -> 5.7 months from Jan 2027 ≈ May 2027 | (migration $121,370 + AWS overlap $24,791) ÷ monthly saving
A14: PHASE 1 — MIGRATION PERIOD (Jul 1, 2026 – Dec 31, 2026) | AWS ramps up month by month | HubStor steps down as Azure regions deleted from Oct
A15: Migration cost distributed across 6 months by activity: data-transfer costs follow the data ramp | gateway installs match each site go-live | testing & decommission back-loaded to Nov–Dec
A16: # | B16: Calendar Month | C16: HubStor + Azure ($) [ramps ↓ from Oct] | D16: AWS Total ($) [ramps ↑ all 6 months] | E16: Combined Spend ($) | F16: Migration Cost ($) [distributed by activity] | G16: Migration Cost — What's included | H16: Net Cumulative Saving ($) [vs doing nothing]
A17: 1 | B17: Jul 2026 | C17: 29455.17 | D17: 1559.61 | E17: =C17+D17+F17 -> 55068.83 | F17: 24054.05 | G17: 1 Gateway EC2 live (WLM pilot). S3~33%. DataSync migrating US-East. | H17: =-SUM(D17:D17)-SUM(F17:F17) -> -25613.66
A18: 2 | B18: Aug 2026 | C18: 29455.17 | D18: 2700.82 | E18: =C18+D18+F18 -> 49509.02 | F18: 17353.03 | G18: 2 Gateway ECs live (WLM+MWN). S3~61%. DataSync US regions. | H18: =-SUM(D17:D18)-SUM(F17:F18) -> -45667.51
A19: 3 | B19: Sep 2026 | C19: 29455.17 | D19: 4202.83 | E19: =C19+D19+F19 -> 62213.06 | F19: 28555.06 | G19: 3 Gateway ECs live (+CRP/UK). S3~99%. DataSync EU-UK. | H19: =-SUM(D17:D19)-SUM(F17:F19) -> -78425.4
A20: 4 | B20: Oct 2026 | C20: 26530.12 | D20: 3174.44 | E20: =C20+D20+F20 -> 52988.61 | F20: 23284.05 | G20: 4 Gateway ECs live (+FRI). S3 rebuilding after WestUS2+DE deletions. | H20: =-SUM(D17:D20)-SUM(F17:F20) -> -104883.89
A21: 5 | B21: Nov 2026 | C21: 11299.36 | D21: 4423.89 | E21: =C21+D21+F21 -> 30705.68 | F21: 14982.43 | G21: 5 Gateway ECs live (all sites). S3~98%. UKSouth+EastUS2 deleted. | H21: =-SUM(D17:D21)-SUM(F17:F21) -> -124290.21
A22: 6 | B22: Dec 2026 | C22: 4000 | D22: 4496.05 | E22: =C22+D22+F22 -> 21637.67 | F22: 13141.62 | G22: All 5 Gateways. S3=100%. All Azure decommissioned. Full steady state. | H22: =-SUM(D17:D22)-SUM(F17:F22) -> -141927.88
A23: 6 mo | B23: MIGRATION TOTAL Jul–Dec 2026 | C23: =SUM(C17:C22) -> 130194.99 | D23: =SUM(D17:D22) -> 20557.64 | E23: =SUM(E17:E22) -> 272122.87 | F23: =SUM(F17:F22) -> 121370.24 | G23: ↑ Extra cost vs doing nothing = AWS overlap ($24,791) + migration ($121,370) = $146,161 | Payback ~4.5 months from Jan 2027 ≈ May 2027 | H23: =H22 -> -141927.88
A24: Migration cost breakdown: Jul $24,054 (setup+20% data) | Aug $17,353 (15% data) | Sep $28,555 (25% data — UK batch) | Oct $23,284 (20% data) | Nov $14,982 (12% data+testing) | Dec $13,142 (8% data+decomm) → Total = $121,370
A26: PHASE 2 — AWS ONLY (Jan 2027 – Dec 2030) | HubStor fully terminated. Azure Blob = $0. Pure AWS spend.
A27: AWS storage grows with data volume: 5% per year from 2028. Column E = monthly saving vs current HubStor baseline.
A28: # | B28: Calendar Month | C28: HubStor + Azure ($) [= $0 from Jan 2027] | D28: AWS Total ($) | E28: Monthly Saving vs HubStor ($) | F28: Cumul. Saving since Jan 2027 ($) | G28: — | H28: Net Cumulative Saving ($) [negative = recovering investment positive = net ahead vs doing nothing]
A29: 8 | B29: Jan 2027 | C29: 0 | D29: =$B$6 -> 4496.0458 | E29: =$B$5-$B$6 -> 24959.124 | F29: =SUM($E$29:E29) -> 24959.124 | G29: 0 | H29: =H23+E29 -> -116968.76
A30: 9 | B30: Feb 2027 | C30: 0 | D30: =$B$6 -> 4496.0458 | E30: =$B$5-$B$6 -> 24959.124 | F30: =SUM($E$29:E30) -> 49918.248 | G30: 0 | H30: =H29+E30 -> -92009.632
A31: 10 | B31: Mar 2027 | C31: 0 | D31: =$B$6 -> 4496.0458 | E31: =$B$5-$B$6 -> 24959.124 | F31: =SUM($E$29:E31) -> 74877.373 | G31: 0 | H31: =H30+E31 -> -67050.507
A32: 11 | B32: Apr 2027 | C32: 0 | D32: =$B$6 -> 4496.0458 | E32: =$B$5-$B$6 -> 24959.124 | F32: =SUM($E$29:E32) -> 99836.497 | G32: 0 | H32: =H31+E32 -> -42091.383
A33: 12 | B33: May 2027 | C33: 0 | D33: =$B$6 -> 4496.0458 | E33: =$B$5-$B$6 -> 24959.124 | F33: =SUM($E$29:E33) -> 124795.62 | G33: 0 | H33: =H32+E33 -> -17132.259
A34: 13 | B34: Jun 2027 | C34: 0 | D34: =$B$6 -> 4496.0458 | E34: =$B$5-$B$6 -> 24959.124 | F34: =SUM($E$29:E34) -> 149754.75 | G34: 0 | H34: =H33+E34 -> 7826.8654
A35: 14 | B35: Jul 2027 | C35: 0 | D35: =$B$6 -> 4496.0458 | E35: =$B$5-$B$6 -> 24959.124 | F35: =SUM($E$29:E35) -> 174713.87 | G35: 0 | H35: =H34+E35 -> 32785.99
A36: 15 | B36: Aug 2027 | C36: 0 | D36: =$B$6 -> 4496.0458 | E36: =$B$5-$B$6 -> 24959.124 | F36: =SUM($E$29:E36) -> 199672.99 | G36: 0 | H36: =H35+E36 -> 57745.114
A37: 16 | B37: Sep 2027 | C37: 0 | D37: =$B$6 -> 4496.0458 | E37: =$B$5-$B$6 -> 24959.124 | F37: =SUM($E$29:E37) -> 224632.12 | G37: 0 | H37: =H36+E37 -> 82704.238
A38: 17 | B38: Oct 2027 | C38: 0 | D38: =$B$6 -> 4496.0458 | E38: =$B$5-$B$6 -> 24959.124 | F38: =SUM($E$29:E38) -> 249591.24 | G38: 0 | H38: =H37+E38 -> 107663.36
A39: 18 | B39: Nov 2027 | C39: 0 | D39: =$B$6 -> 4496.0458 | E39: =$B$5-$B$6 -> 24959.124 | F39: =SUM($E$29:E39) -> 274550.37 | G39: 0 | H39: =H38+E39 -> 132622.49
A40: 19 | B40: Dec 2027 | C40: 0 | D40: =$B$6 -> 4496.0458 | E40: =$B$5-$B$6 -> 24959.124 | F40: =SUM($E$29:E40) -> 299509.49 | G40: 0 | H40: =H39+E40 -> 157581.61
A41: 20 | B41: Jan 2028 | C41: 0 | D41: =$B$6*(1+$B$8) -> 4720.8481 | E41: =$B$5-$B$6*(1+$B$8) -> 24734.322 | F41: =SUM($E$29:E41) -> 324243.81 | G41: 0 | H41: =H40+E41 -> 182315.93
A42: 21 | B42: Feb 2028 | C42: 0 | D42: =$B$6*(1+$B$8) -> 4720.8481 | E42: =$B$5-$B$6*(1+$B$8) -> 24734.322 | F42: =SUM($E$29:E42) -> 348978.13 | G42: 0 | H42: =H41+E42 -> 207050.25
A43: 22 | B43: Mar 2028 | C43: 0 | D43: =$B$6*(1+$B$8) -> 4720.8481 | E43: =$B$5-$B$6*(1+$B$8) -> 24734.322 | F43: =SUM($E$29:E43) -> 373712.46 | G43: 0 | H43: =H42+E43 -> 231784.58
A44: 23 | B44: Apr 2028 | C44: 0 | D44: =$B$6*(1+$B$8) -> 4720.8481 | E44: =$B$5-$B$6*(1+$B$8) -> 24734.322 | F44: =SUM($E$29:E44) -> 398446.78 | G44: 0 | H44: =H43+E44 -> 256518.9
A45: 24 | B45: May 2028 | C45: 0 | D45: =$B$6*(1+$B$8) -> 4720.8481 | E45: =$B$5-$B$6*(1+$B$8) -> 24734.322 | F45: =SUM($E$29:E45) -> 423181.1 | G45: 0 | H45: =H44+E45 -> 281253.22
A46: 25 | B46: Jun 2028 | C46: 0 | D46: =$B$6*(1+$B$8) -> 4720.8481 | E46: =$B$5-$B$6*(1+$B$8) -> 24734.322 | F46: =SUM($E$29:E46) -> 447915.42 | G46: 0 | H46: =H45+E46 -> 305987.54
A47: 26 | B47: Jul 2028 | C47: 0 | D47: =$B$6*(1+$B$8) -> 4720.8481 | E47: =$B$5-$B$6*(1+$B$8) -> 24734.322 | F47: =SUM($E$29:E47) -> 472649.74 | G47: 0 | H47: =H46+E47 -> 330721.86
A48: 27 | B48: Aug 2028 | C48: 0 | D48: =$B$6*(1+$B$8) -> 4720.8481 | E48: =$B$5-$B$6*(1+$B$8) -> 24734.322 | F48: =SUM($E$29:E48) -> 497384.07 | G48: 0 | H48: =H47+E48 -> 355456.19
A49: 28 | B49: Sep 2028 | C49: 0 | D49: =$B$6*(1+$B$8) -> 4720.8481 | E49: =$B$5-$B$6*(1+$B$8) -> 24734.322 | F49: =SUM($E$29:E49) -> 522118.39 | G49: 0 | H49: =H48+E49 -> 380190.51
A50: 29 | B50: Oct 2028 | C50: 0 | D50: =$B$6*(1+$B$8) -> 4720.8481 | E50: =$B$5-$B$6*(1+$B$8) -> 24734.322 | F50: =SUM($E$29:E50) -> 546852.71 | G50: 0 | H50: =H49+E50 -> 404924.83
A51: 30 | B51: Nov 2028 | C51: 0 | D51: =$B$6*(1+$B$8) -> 4720.8481 | E51: =$B$5-$B$6*(1+$B$8) -> 24734.322 | F51: =SUM($E$29:E51) -> 571587.03 | G51: 0 | H51: =H50+E51 -> 429659.15
A52: 31 | B52: Dec 2028 | C52: 0 | D52: =$B$6*(1+$B$8) -> 4720.8481 | E52: =$B$5-$B$6*(1+$B$8) -> 24734.322 | F52: =SUM($E$29:E52) -> 596321.35 | G52: 0 | H52: =H51+E52 -> 454393.47
A53: 32 | B53: Jan 2029 | C53: 0 | D53: =$B$6*(1+$B$8)^2 -> 4956.8905 | E53: =$B$5-$B$6*(1+$B$8)^2 -> 24498.28 | F53: =SUM($E$29:E53) -> 620819.63 | G53: 0 | H53: =H52+E53 -> 478891.75
A54: 33 | B54: Feb 2029 | C54: 0 | D54: =$B$6*(1+$B$8)^2 -> 4956.8905 | E54: =$B$5-$B$6*(1+$B$8)^2 -> 24498.28 | F54: =SUM($E$29:E54) -> 645317.91 | G54: 0 | H54: =H53+E54 -> 503390.03
A55: 34 | B55: Mar 2029 | C55: 0 | D55: =$B$6*(1+$B$8)^2 -> 4956.8905 | E55: =$B$5-$B$6*(1+$B$8)^2 -> 24498.28 | F55: =SUM($E$29:E55) -> 669816.19 | G55: 0 | H55: =H54+E55 -> 527888.31
A56: 35 | B56: Apr 2029 | C56: 0 | D56: =$B$6*(1+$B$8)^2 -> 4956.8905 | E56: =$B$5-$B$6*(1+$B$8)^2 -> 24498.28 | F56: =SUM($E$29:E56) -> 694314.47 | G56: 0 | H56: =H55+E56 -> 552386.59
A57: 36 | B57: May 2029 | C57: 0 | D57: =$B$6*(1+$B$8)^2 -> 4956.8905 | E57: =$B$5-$B$6*(1+$B$8)^2 -> 24498.28 | F57: =SUM($E$29:E57) -> 718812.75 | G57: 0 | H57: =H56+E57 -> 576884.87
A58: 37 | B58: Jun 2029 | C58: 0 | D58: =$B$6*(1+$B$8)^2 -> 4956.8905 | E58: =$B$5-$B$6*(1+$B$8)^2 -> 24498.28 | F58: =SUM($E$29:E58) -> 743311.03 | G58: 0 | H58: =H57+E58 -> 601383.15
A59: 38 | B59: Jul 2029 | C59: 0 | D59: =$B$6*(1+$B$8)^2 -> 4956.8905 | E59: =$B$5-$B$6*(1+$B$8)^2 -> 24498.28 | F59: =SUM($E$29:E59) -> 767809.31 | G59: 0 | H59: =H58+E59 -> 625881.43
A60: 39 | B60: Aug 2029 | C60: 0 | D60: =$B$6*(1+$B$8)^2 -> 4956.8905 | E60: =$B$5-$B$6*(1+$B$8)^2 -> 24498.28 | F60: =SUM($E$29:E60) -> 792307.59 | G60: 0 | H60: =H59+E60 -> 650379.71
A61: 40 | B61: Sep 2029 | C61: 0 | D61: =$B$6*(1+$B$8)^2 -> 4956.8905 | E61: =$B$5-$B$6*(1+$B$8)^2 -> 24498.28 | F61: =SUM($E$29:E61) -> 816805.87 | G61: 0 | H61: =H60+E61 -> 674877.99
A62: 41 | B62: Oct 2029 | C62: 0 | D62: =$B$6*(1+$B$8)^2 -> 4956.8905 | E62: =$B$5-$B$6*(1+$B$8)^2 -> 24498.28 | F62: =SUM($E$29:E62) -> 841304.15 | G62: 0 | H62: =H61+E62 -> 699376.27
A63: 42 | B63: Nov 2029 | C63: 0 | D63: =$B$6*(1+$B$8)^2 -> 4956.8905 | E63: =$B$5-$B$6*(1+$B$8)^2 -> 24498.28 | F63: =SUM($E$29:E63) -> 865802.43 | G63: 0 | H63: =H62+E63 -> 723874.55
A64: 43 | B64: Dec 2029 | C64: 0 | D64: =$B$6*(1+$B$8)^2 -> 4956.8905 | E64: =$B$5-$B$6*(1+$B$8)^2 -> 24498.28 | F64: =SUM($E$29:E64) -> 890300.71 | G64: 0 | H64: =H63+E64 -> 748372.83
A65: 44 | B65: Jan 2030 | C65: 0 | D65: =$B$6*(1+$B$8)^3 -> 5204.735 | E65: =$B$5-$B$6*(1+$B$8)^3 -> 24250.435 | F65: =SUM($E$29:E65) -> 914551.14 | G65: 0 | H65: =H64+E65 -> 772623.26
A66: 45 | B66: Feb 2030 | C66: 0 | D66: =$B$6*(1+$B$8)^3 -> 5204.735 | E66: =$B$5-$B$6*(1+$B$8)^3 -> 24250.435 | F66: =SUM($E$29:E66) -> 938801.58 | G66: 0 | H66: =H65+E66 -> 796873.7
A67: 46 | B67: Mar 2030 | C67: 0 | D67: =$B$6*(1+$B$8)^3 -> 5204.735 | E67: =$B$5-$B$6*(1+$B$8)^3 -> 24250.435 | F67: =SUM($E$29:E67) -> 963052.01 | G67: 0 | H67: =H66+E67 -> 821124.13
A68: 47 | B68: Apr 2030 | C68: 0 | D68: =$B$6*(1+$B$8)^3 -> 5204.735 | E68: =$B$5-$B$6*(1+$B$8)^3 -> 24250.435 | F68: =SUM($E$29:E68) -> 987302.45 | G68: 0 | H68: =H67+E68 -> 845374.57
A69: 48 | B69: May 2030 | C69: 0 | D69: =$B$6*(1+$B$8)^3 -> 5204.735 | E69: =$B$5-$B$6*(1+$B$8)^3 -> 24250.435 | F69: =SUM($E$29:E69) -> 1011552.9 | G69: 0 | H69: =H68+E69 -> 869625
A70: 49 | B70: Jun 2030 | C70: 0 | D70: =$B$6*(1+$B$8)^3 -> 5204.735 | E70: =$B$5-$B$6*(1+$B$8)^3 -> 24250.435 | F70: =SUM($E$29:E70) -> 1035803.3 | G70: 0 | H70: =H69+E70 -> 893875.44
A71: 50 | B71: Jul 2030 | C71: 0 | D71: =$B$6*(1+$B$8)^3 -> 5204.735 | E71: =$B$5-$B$6*(1+$B$8)^3 -> 24250.435 | F71: =SUM($E$29:E71) -> 1060053.8 | G71: 0 | H71: =H70+E71 -> 918125.87
A72: 51 | B72: Aug 2030 | C72: 0 | D72: =$B$6*(1+$B$8)^3 -> 5204.735 | E72: =$B$5-$B$6*(1+$B$8)^3 -> 24250.435 | F72: =SUM($E$29:E72) -> 1084304.2 | G72: 0 | H72: =H71+E72 -> 942376.31
A73: 52 | B73: Sep 2030 | C73: 0 | D73: =$B$6*(1+$B$8)^3 -> 5204.735 | E73: =$B$5-$B$6*(1+$B$8)^3 -> 24250.435 | F73: =SUM($E$29:E73) -> 1108554.6 | G73: 0 | H73: =H72+E73 -> 966626.74
A74: 53 | B74: Oct 2030 | C74: 0 | D74: =$B$6*(1+$B$8)^3 -> 5204.735 | E74: =$B$5-$B$6*(1+$B$8)^3 -> 24250.435 | F74: =SUM($E$29:E74) -> 1132805.1 | G74: 0 | H74: =H73+E74 -> 990877.18
A75: 54 | B75: Nov 2030 | C75: 0 | D75: =$B$6*(1+$B$8)^3 -> 5204.735 | E75: =$B$5-$B$6*(1+$B$8)^3 -> 24250.435 | F75: =SUM($E$29:E75) -> 1157055.5 | G75: 0 | H75: =H74+E75 -> 1015127.6
A76: 55 | B76: Dec 2030 | C76: 0 | D76: =$B$6*(1+$B$8)^3 -> 5204.735 | E76: =$B$5-$B$6*(1+$B$8)^3 -> 24250.435 | F76: =SUM($E$29:E76) -> 1181305.9 | G76: 0 | H76: =H75+E76 -> 1039378
A78: ANNUAL SUMMARY
A79: Period | B79: Calendar Year | C79: HubStor + Azure ($) | D79: AWS Total ($) | E79: Gross Saving ($) | F79: Migration / One-time ($) | G79: Net Saving ($) | H79: Cumul. Net Saving ($) | I79: Row reference
A80: Phase 1 | B80: Jul–Dec 2026 (migration) | C80: =SUM(C17:C22) -> 130194.99 | D80: =SUM(D17:D22) -> 20557.64 | E80: - | F80: =SUM(F17:F22) -> 121370.24 | G80: =H23 -> -141927.88 | H80: =H23 -> -141927.88 | I80: R17–R22
A81: Year 1 | B81: Jan–Dec 2027 | C81: =SUM(C29:C40) -> 0 | D81: =SUM(D29:D40) -> 53952.549 | E81: =$B$5*12-SUM(D29:D40) -> 299509.49 | F81: 0 | G81: =$B$5*12-SUM(D29:D40) -> 299509.49 | H81: =H80+G81 -> 157581.61 | I81: R29–R40
A82: Year 2 | B82: Jan–Dec 2028 | C82: =SUM(C41:C52) -> 0 | D82: =SUM(D41:D52) -> 56650.177 | E82: =$B$5*12-SUM(D41:D52) -> 296811.86 | F82: 0 | G82: =$B$5*12-SUM(D41:D52) -> 296811.86 | H82: =H81+G82 -> 454393.47 | I82: R41–R52
A83: Year 3 | B83: Jan–Dec 2029 | C83: =SUM(C53:C64) -> 0 | D83: =SUM(D53:D64) -> 59482.686 | E83: =$B$5*12-SUM(D53:D64) -> 293979.35 | F83: 0 | G83: =$B$5*12-SUM(D53:D64) -> 293979.35 | H83: =H82+G83 -> 748372.83 | I83: R53–R64
A84: Year 4 | B84: Jan–Dec 2030 | C84: =SUM(C65:C76) -> 0 | D84: =SUM(D65:D76) -> 62456.82 | E84: =$B$5*12-SUM(D65:D76) -> 291005.22 | F84: 0 | G84: =$B$5*12-SUM(D65:D76) -> 291005.22 | H84: =H83+G84 -> 1039378 | I84: R65–R76
A85: TOTAL | B85: Jun 2026 – Dec 2030 | C85: =SUM(C80:C84) -> 130194.99 | D85: =SUM(D80:D84) -> 253099.87 | E85: =SUM(E80:E84) -> 1181305.9 | F85: =SUM(F80:F84) -> 121370.24 | G85: =H23+SUM(G81:G84) -> 1039378 | H85: =H84 -> 1039378 | I85: R17–R76

Sheet Migration Architecture
A1: MIGRATION ARCHITECTURE — AWS S3 File Gateway VM (EC2 t3.xlarge per site, recurring monthly)
A2: PROPOSAL: File Gateway VM on EC2 t3.xlarge at each of the 5 sites. RECURRING cost: $130/mo/site × 5 = $650/mo from the moment each gateway goes live. MIGRATION (Jul–Dec 2026): DataSync migrates historical data Azure→S3; Gateway handles new writes from cutover. POST-MIGRATION (Jan 2027+): Gateway is sole connectivity layer. AWS Total = $4,496/mo.
A4: DIAGRAM 1 — MIGRATION PERIOD (Jul–Dec 2026) | DataSync migrates historical data | Gateway EC2 launched per-site, handles new writes
A5: DataSync (EC2 agent in AWS) migrates all Azure Blob data directly to S3 — Gateway not used for this. File Gateway EC2 launched site-by-site during migration; recurring $130/mo charge starts immediately. Gateway starts serving new writes from each site on its cutover date.
A59: MIGRATION COST VALIDATION — One-time costs (Jul–Dec 2026)
A60: Component | B60: Role | C60: One-time cost | D60: How it works | E60: Note
A61: AWS DataSync | B61: REQUIRED — migration tool | C61: $14,321 | D61: Reads Azure Blob → writes to S3. EC2 agent in AWS. $0.0125/GB × 1,145,641 GB. | E61: ✅ Stops when migration completes.
A62: Azure retrieval fees | B62: REQUIRED — unavoidable | C62: $22,739 | D62: Azure charges: Cool $0.01/GB · Cold $0.03/GB · Archive $0.022/GB. Standard/Hot = free. | E62: ✅ Negotiate Azure egress waiver first.
A63: Azure egress charges | B63: REQUIRED — unavoidable | C63: $64,645 | D63: Azure internet egress Azure→S3. Tiered $0.087→$0.05/GB. | E63: ⚠ Request Azure credits — could save $30–60K.
A64: File Gateway EC2 setup — 5 sites | B64: REQUIRED — launch during migration | C64: $2,500 | D64: $500/site IT config × 5. Launch EC2 t3.xlarge, install Gateway, configure NFS/SMB shares. | E64: ✅ Recurring $130/mo/site starts on launch. Gateway handles new writes, not migration data.
A65: IAM · KMS · S3 bucket config | B65: REQUIRED — Week 1 | C65: $1,500 | D65: 5 S3 buckets, lifecycle, Object Lock, IAM roles, KMS CMKs. | E65: ✅ Complete before DataSync starts.
A66: S3 PUT requests | B66: REQUIRED — ingestion | C66: $436 | D66: $0.005–$0.05/1K objects. PUT directly to target storage class. | E66: ✅ Use --storage-class flag in DataSync.
A67: Testing · UAT · HubStor decommission | B67: REQUIRED | C67: $5,000 | D67: UAT $3,000 + HubStor contract decommission $2,000. | E67: ✅ 100% object match before each cutover.
A68: Contingency 10% | B68: RECOMMENDED | C68: $10,921 | D68: 10% buffer for egress spikes, retries, delays. | E68: ✅ Standard for cross-cloud migrations.
A69: GRAND TOTAL — ONE-TIME | C69: ~$121,062 | D69: Note: Gateway EC2 recurring cost ($650/mo) is separate — starts during migration, continues permanently.
A71: DIAGRAM 2 — POST-MIGRATION STEADY STATE (Jan 2027+) | Gateway EC2 $650/mo recurring | AWS Total = $4,496/mo
A72: File Gateway EC2 t3.xlarge ($130/mo/site × 5 = $650/mo) is a permanent RECURRING cost — same as paying for any cloud VM. This is the price of replacing HubStor connectors with a managed AWS connectivity layer. AWS Total = S3 $3,608 + Gateway EC2 $650 + ops $238 = $4,496/mo. This is consistent across Cost Comparison B39, Financial Model B6, and Executive Summary KPI tile.
A126: ONGOING AWS COST VALIDATION — Monthly recurring from Jan 2027 | $4,496/mo total
A127: Resource | B127: Needed? | C127: Qty | D127: Unit/mo | E127: Monthly | F127: Annual | G127: Validation
A128: S3 storage — all 5 tiers | B128: YES | C128: 1,041.7 TiB | D128: $3,608 | E128: $3,608 | F128: $43,296 | G128: Core storage. Standard/IA/Glacier IR/Deep Archive. Grows 5%/yr from 2028.
A129: File Gateway EC2 — t3.xlarge × 5 | B129: YES — RECURRING | C129: ×5 EC2 | D129: $130 | E129: $650 | F129: $7,800 | G129: RECURRING monthly. EC2 compute for File Gateway VM at each site. Permanent connectivity layer.
A130: Hardware Appliance | B130: NOT PURCHASED | C130: — | D130: $0 | E130: $0 | F130: $0 | G130: Physical unit not purchased. EC2 instance used instead. Assumptions C51=$130 (EC2 cost).
A131: CloudWatch | B131: YES | C131: 1 | D131: $31 | E131: $31 | F131: $372 | G131: Dashboards, alarms, cost anomaly detection.
A132: KMS keys | B132: YES | C132: 5 keys | D132: $1 | E132: $5 | F132: $60 | G132: SSE-KMS per region.
A133: SNS alerts | B133: YES | C133: 1 | D133: $2 | E133: $2 | F133: $24 | G133: Budget and Gateway health alerts.
A134: AWS Config | B134: YES | C134: 1 | D134: $10 | E134: $10 | F134: $120 | G134: S3 compliance monitoring.
A135: S3 API operations | B135: YES | C135: 1 | D135: $65 | E135: $65 | F135: $780 | G135: PUTs from Gateway + GETs for retrieval.
A136: Glacier retrieval | B136: YES | C136: 1 | D136: $86 | E136: $86 | F136: $1,032 | G136: 0.5% of archive/mo × $0.02/GB.
A137: Internet egress | B137: YES | C137: 1 | D137: $39 | E137: $39 | F137: $468 | G137: ~10% retrieved externally.
A138: S3 Transfer Acceleration | B138: NOT NEEDED | C138: — | D138: $0 | E138: $0 | F138: $0 | G138: Standard HTTPS sufficient.
A139: DataSync | B139: STOPPED | C139: — | D139: $0 | E139: $0 | F139: $0 | G139: Migration done. EC2 agent terminated.
A140: AWS TOTAL (Jan 2027+) | E140: $4,496/mo | F140: $53,952/yr | G140: S3 $3,608 + Gateway EC2 $650 + CW $31 + KMS $5 + SNS $2 + Config $10 + API $65 + Glacier $86 + Egress $39 = $4,496

Sheet Architecture & Connectivity
A1: AWS S3 TARGET ARCHITECTURE — CONNECTIVITY & ACCESS DESIGN
A2: Full HubStor replacement | S3 File Gateway replaces all HubStor connectors | Data residency preserved per region
A4: STORAGE GATEWAY — HOW SITES CONNECT TO S3 POST-MIGRATION (replaces HubStor connectors)
A5: Pattern | B5: AWS S3 File Gateway (NFS/SMB shares) → replaces every HubStor connector agent at each site. S3-compatible. No application changes needed.
A6: What it is | B6: AWS S3 File Gateway (software VM) deployed on CRL's EXISTING on-prem server at each site (VMware / Hyper-V / KVM — same servers that run HubStor connector agents today). Presents NFS or SMB file shares to local applications. Caches recent files locally (1TB on existing server disk). Uploads new files to S3 automatically over HTTPS. NO Hardware Appliance purchased. Software is free — only S3 storage costs apply.
A7: Archiving flow | B7: Application saves file → File Gateway share → Gateway caches locally → Compresses & uploads to S3 bucket (correct storage class via lifecycle rule) → File stays accessible via share (cached read).
A8: Retrieval flow | B8: User requests file from Gateway share → Gateway checks local 1TB EBS cache → If cached: instant return → If not cached: fetches from S3 (Standard-IA: ms; Glacier IR: ms; Deep Archive: restore first ~12-48hr) → Returns file.
A9: Sites & VMs | B9: 5 Gateway VMs required: • WLM (EastUS2) → us-east-1 • RNO (WestUS2) → us-west-2 • UK sites (UKSouth) → eu-west-2 • NL/EU sites (WestEurope) → eu-west-1 • DE site (GermanyWestCentral) → eu-central-1
A10: HubStor connectors replaced | B10: All 17+ DPI connectors (APO-PR-APP-*), NAS connectors (MWN-PR-FIL-01, WLM-PR-FIL-05), and test connectors replaced by gateway shares. One Gateway per site serves all connectors at that site.
A11: Migration tool | B11: AWS DataSync for bulk one-time migration (Azure Blob → S3). DataSync handles checksums, retry, parallelism. Post-migration: Gateway handles all incremental writes; DataSync not needed.
A13: S3 BUCKET STRATEGY
A14: Bucket per region (5 buckets) | B14: us-east-1: company-archive-us-east / us-west-2: company-archive-us-west / eu-west-2: company-archive-uk / eu-west-1: company-archive-eu / eu-central-1: company-archive-de
A15: Prefix / key structure | B15: s3://company-archive-{region}/{site-code}/{stor-name}/{year}/{month}/{filename} e.g., s3://company-archive-uk/CRP/EarlyDiscovery/2024/03/sample.raw
A16: Storage class mapping | B16: Standard/Hot → S3 Standard | Cool → S3 Standard-IA (lifecycle Day 0) | Cold → S3 Glacier Instant Retrieval | Archive → S3 Glacier Deep Archive (PUT directly via --storage-class)
A17: Lifecycle rules | B17: Lifecycle rule 1: Objects with tag tier=cool → Standard-IA immediately. Rule 2: Objects with tag tier=archive → Glacier Deep Archive immediately. Rule 3: Incomplete multipart uploads → abort after 7 days.
A18: Object Lock (GxP data) | B18: Enable S3 Object Lock in Compliance mode on buckets holding GxP-regulated data (Safety Assessment, Microbial). Retention period = defined by QA/Regulatory team. Objects cannot be deleted or modified during retention.
A19: Versioning | B19: Enable ONLY on compliance/GxP buckets. Do NOT enable on pure archive buckets (versioning doubles storage cost for every overwrite).
A20: Encryption | B20: SSE-S3 (AES-256) at zero extra cost as baseline. Upgrade to SSE-KMS for GxP data requiring audit trail of key access. 1 KMS CMK per region = $5/month total.
A21: VPC Gateway Endpoint | B21: Deploy free S3 VPC Gateway Endpoint in each AWS region to route S3 traffic within AWS backbone — eliminates NAT Gateway data processing charges if any EC2-based processing is added later.
A23: CONNECTIVITY OPTIONS
A24: Option A — HTTPS/TLS (Recommended, chosen for this design) | B24: Gateway VM uploads to S3 public endpoint over port 443 (HTTPS). Data is encrypted in transit (TLS 1.2+). No additional cost. All current sites have reliable internet. This is the chosen architecture.
A25: Option B — AWS Site-to-Site VPN (optional add-on) | B25: ~$0.05/hr per VPN connection = $36/mo. Use if security policy requires private connectivity. Can be added after cutover. Transit cost ~$0.01/GB within AWS. NOT required for launch.
A26: Option C — AWS Direct Connect (optional premium) | B26: Dedicated 1Gbps circuit ~$200-500/mo port cost. Use only if bandwidth becomes a demonstrated bottleneck after 3 months on Option A. Overkill for archive workloads.
A27: Recommendation | B27: Launch with Option A. Monitor Gateway CloudWatch metric WriteBytesPerSecond. If consistently >50MB/s sustained and latency is causing issues, evaluate Option B as next step.
A29: REGION MAPPING — AZURE → AWS (data residency preserved)
A30: Azure EastUS2 (Virginia, USA) | B30: → AWS us-east-1 (N. Virginia) | Sites: MWN, WLM | Safety Assessment East, Microbial, RMS
A31: Azure WestUS2 (Washington, USA) | B31: → AWS us-west-2 (Oregon) | Sites: RNO | Safety Assessment West
A32: Azure UKSouth (London, UK) | B32: → AWS eu-west-2 (London) | Sites: CRP, HAR, PTH, EDI | UK data stays in UK ✓
A33: Azure WestEurope (Amsterdam, NL) | B33: → AWS eu-west-1 (Ireland) | Sites: LEI, HER, GRO, KUO, SZG, FRE, LYO, EVR | EU data stays in EU ✓
A34: Azure GermanyWestCentral (Frankfurt) | B34: → AWS eu-central-1 (Frankfurt) | Sites: FRI | German data stays in Germany (GDPR) ✓
A35: GDPR / Data Sovereignty | B35: No data crosses borders. UK data: eu-west-2 (London). German data: eu-central-1 (Frankfurt). All EU data in EU. S3 bucket region is enforced by SCP (Service Control Policy) blocking bucket creation in wrong regions.
